{
  "lecture_date": "2026-02-26",
  "pass_num": 0,
  "transcript_path": "/Users/youngjinson/멋사-인턴/NLP 과제 1 - AI 강의 분석 리포트 생성기/강의 스크립트/2026-02-26_kdt-backendj-21th.txt",
  "metadata": {
    "course_id": "",
    "course_name": "백엔드 부트캠프 21기: Java",
    "date": "2026-02-26",
    "subjects": [
      "Back-End Programming"
    ],
    "contents": [
      "HTTP 통신 개요 및 웹 작동 방식"
    ],
    "instructor": "김영아",
    "sub_instructors": [
      "김다은",
      "정석현"
    ]
  },
  "category_results": [
    {
      "category_name": "1. 언어 표현 품질",
      "items": [
        {
          "item_id": "1.1",
          "item_name": "불필요한 반복 표현",
          "category": "1. 언어 표현 품질",
          "score": 3,
          "weight": "HIGH",
          "evidence": [
            "<09:10:51> ... 저희 어제 살짝 내용 전체 확인하고 그 다음에 저희 오늘 이어서 진행을 할 거고요.",
            "<09:11:07> ... 저희가 만약에 데이터베이스를 서버에 접속을 하려고 그러면 ...",
            "<09:11:24> ... 그 다음에 권한을 설정을 하고 권한을 삭제를 하는 ...",
            "<09:20:37> ... 그래서 ...",
            "<09:22:36> ... 저희는 실제 루트가 가장 높다는 거죠 ...",
            "<09:30:07> ... 이렇게 접속이 가능해가죠 수업할 때는 ...",
            "<09:30:39> ... 이제 ...",
            "<09:31:47> ... 자 ...",
            "<09:31:58> ... 다시 옵니다 ...",
            "<09:41:47> ... 이제 얘네가 가지고 있는 기본 정보들은 다 확인을 했고 ..."
          ],
          "reasoning": "습관적 표현 '저희'가 여러 번 반복되며, '그 다음에'와 같은 연결어도 빈번하게 사용됨. 분당 약 4회 관찰됨. | 습관적 표현 '그래서'와 '저희'가 여러 차례 반복되어 나타나며, 특히 '그래서'는 분당 약 3회 관찰됨. 강의 흐름에 큰 문제는 없으나 반복이 눈에 띔. | 습관적 표현 '이제'와 '자'가 해당 구간에서 각각 3회 관찰됨. 반복이 있지만 내용 전달에 큰 문제는 없음.",
          "confidence": 0.78,
          "caveats": [
            "STT 오인식으로 인한 반복 가능성 일부 존재"
          ]
        },
        {
          "item_id": "1.2",
          "item_name": "발화 완결성",
          "category": "1. 언어 표현 품질",
          "score": 3,
          "weight": "MEDIUM",
          "evidence": [
            "<09:11:10> ... 그 다음에 권한 부여받고 그 다음에 객체에 접근할 수 있는 이런 3단계가 있습니다.",
            "<09:11:37> ... 끝나면 그 다음에 트리거 이용을 해서 어떤 식으로 데이터가 자동 실행을 한꺼번에 할 수 있는지를 확인해 보도록 할게요.",
            "<09:20:37> ... 그래서 우리가 지금 사용하고 있는 이쪽에 저희가 만들어 놓은 스키마 이제 마이에스큐 시리즈는 접근할 수는 없지만 ...",
            "<09:30:07> ... 이렇게 접속이 가능해가죠 수업할 때는 ...",
            "<09:31:51> ... 거죠. 이 수업을 ...",
            "<09:32:40> ... 이렇게 해서 하나 둘 넷 다섯 개의 큰 섹션으로 나눠져 있고 ...",
            "<09:40:38> ... 이건 없지만, 기본적으로 사용자 계정은 지금 다 받아온 두 개는 루트만큼 내용을 지금 ...",
            "<09:54:20> ... 작업을 할 수 있는지를 주는 거지 ...",
            "<09:50:31> ... 그래서 여기 이제 유저 테이블에 있는 애들 ...",
            "<09:52:20> ... 생각하시면 조금 편해요 ..."
          ],
          "reasoning": "비완결 문장이 간간이 나타나며, 특히 긴 문장에서 중간에 끊기는 경우가 있어 의미 파악이 어려운 부분이 있음. | 비완결 문장이 간간이 나타나며, 특히 긴 문장에서 주어와 서술어가 명확하지 않은 경우가 있음. 수강생이 의미를 추론해야 하는 경우가 발생. | 비완결 문장이 간간이 나타나며, 특히 문장 중간에 주제가 전환되는 경우가 있어 의미 파악이 어려운 부분이 있음.",
          "confidence": 0.72,
          "caveats": [
            "STT 오류로 인한 문장 끊김 가능성",
            "STT 오류로 인한 문장 끊김은 감점 대상에서 제외"
          ]
        },
        {
          "item_id": "1.3",
          "item_name": "언어 일관성",
          "category": "1. 언어 표현 품질",
          "score": 4,
          "weight": "MEDIUM",
          "evidence": [
            "<09:10:27> ... 안녕하세요. 오늘 수업 진행하도록 하겠습니다.",
            "<09:10:38> ... 저희 어제는 인덱스 구현해서 개념하고 필요성 진행하는 걸 사용을 했었고 ...",
            "<09:20:37> ... 저희가 지금 사용하고 있는 ...",
            "<09:22:36> ... 저희는 실제 루트가 가장 높다는 거죠 ...",
            "<09:30:29> ... 여러분들께 ...",
            "<09:31:47> ... 자 얘네들은 ...",
            "<09:40:38> ... 이렇게 프록시온에 그랜트 옵션을 줄 수 있는 슈퍼유저 ...",
            "<09:52:20> ... 어센디케이션은 누구야 이거니까 계정하고 비밀번호를 확인해야 되니까.",
            "<09:50:31> ... 저희가 ...",
            "<09:51:20> ... 저희가 ..."
          ],
          "reasoning": "대체로 존댓말로 일관되지만, 특정 구간에서 반말이 혼용되는 경향이 있어 약간의 어색함이 존재함. | 대체로 존댓말로 일관되지만, 특정 구간에서 반말이 혼용되는 경향이 있음. 전반적으로는 일관성이 유지되고 있음. | 대체로 존댓말로 일관되지만, 특정 구간에서 반말이 혼용되어 어색함이 느껴짐.",
          "confidence": 0.81,
          "caveats": [
            "수강생과 대화 시 톤 변화는 자연스러운 것으로 봄"
          ]
        }
      ],
      "weighted_average": 3.2857142857142856
    },
    {
      "category_name": "2. 강의 도입 및 구조",
      "items": [
        {
          "item_id": "2.1",
          "item_name": "학습 목표 안내",
          "category": "2. 강의 도입 및 구조",
          "score": 4,
          "weight": "HIGH",
          "evidence": [
            "<09:10:27> 오늘 수업 진행하도록 하겠습니다.",
            "<09:10:38> 오늘은 어제 사용자 개정 권한 저희 어제 살짝 내용 전체 확인하고 그 다음에 저희 오늘 이어서 진행을 할 거고요."
          ],
          "reasoning": "강의 시작 후 1분 이내에 학습 목표를 언급하고 진행 순서를 설명함. '오늘은 어제 사용자 개정 권한...' 부분에서 오늘의 주제를 명확히 제시함.",
          "confidence": 0.85,
          "caveats": []
        },
        {
          "item_id": "2.2",
          "item_name": "전날 복습 연계",
          "category": "2. 강의 도입 및 구조",
          "score": 4,
          "weight": "HIGH",
          "evidence": [
            "<09:10:38> 어제는 인덱스 구현해서 개념하고 필요성 진행하는 걸 사용을 했었고...",
            "<09:10:51> 오늘은 어제 사용자 개정 권한 저희 어제 살짝 내용 전체 확인하고..."
          ],
          "reasoning": "이전 강의 내용을 간략히 언급하며 오늘 내용으로 자연스럽게 전환함. '어제는 인덱스 구현...' 부분에서 복습을 잘 연결함.",
          "confidence": 0.85,
          "caveats": []
        },
        {
          "item_id": "2.3",
          "item_name": "설명 순서",
          "category": "2. 강의 도입 및 구조",
          "score": 2,
          "weight": "MEDIUM",
          "evidence": [
            "<09:11:07> 저희가 만약에 데이터베이스를 서버에 접속을 하려고 그러면 서버에 접속할 수 있는 계정을 먼저 생성하고...",
            "<09:20:37> 걔를 그 뷰의 객체를 얘가 관리한 말 그대로 그래서 우리가 지금 사용하고 있는 이쪽에 저희가 만들어 놓은 스키마 이제 마이에스큐 시리즈는 접근할 수는 없지만...",
            "<09:35:01> 얘는 지금 권한확인인데 그냥 권한 확인이 아니고 현재 로그인 권한 확인이에요.",
            "<09:40:27> 이렇게 프록시온에 그랜트 옵션을 줄 수 있는 슈퍼유저 이건 없지만, 기본적으로 사용자 계정은 지금 다 받아온 두 개는 루트만큼 내용을 지금",
            "<09:54:09> 자 그러면은 일단은 사용자 계정 권한은 어떤 할 수가 있어 권한은 프리빌리지라는 걸 할 수가 있는데, 사용자 또는 역할이 어떤 작업을 어떤 작업을 할 수 있는지를 주는 거지",
            "<10:10:29> 전화를 뭔가를 조작할 수 있는 권한을 전혀 안 받았어.",
            "<10:29:25> 크리에이트 유저 알터 유저 이렇게 뉴유저의 로카 로스트에다가 일단은 뉴 패스워드 이렇게 하나 하고 뉴 테스트도 아까 뉴 테스트 했는데 뉴 1 2 3 확인하고...",
            "<11:01:20> 자 저희가 이제 다시 한번 정리를 좀 해보면 쉬운데 쉬워요...",
            "<11:04:06> 그래서 서버에 어떤 계정이 있는지 한번 확인해 보고 싶다.",
            "<11:20:29> 몇개를 만들던 지금 상관은 없어요."
          ],
          "reasoning": "개념 설명 후 예시를 제시하는 구조는 있지만, 때때로 순서가 뒤바뀌거나 단계가 생략되는 경향이 있음. | 개념, 예시, 실습의 순서가 혼재되어 있으며, 설명이 구조적으로 제시되지 않음. | 개념과 예시가 혼재되어 있지만, 대체로 설명 순서가 유지되고 있음.",
          "confidence": 0.78,
          "caveats": []
        },
        {
          "item_id": "2.4",
          "item_name": "핵심 내용 강조",
          "category": "2. 강의 도입 및 구조",
          "score": 2,
          "weight": "MEDIUM",
          "evidence": [
            "<09:15:38> 사용자 생성 이런 모든 제어가 가능한 게 루트 저희가 맨 처음에 수업을 할 때 루뜨로 왔단 말이야.",
            "<09:20:37> 걔를 그 뷰의 객체를 얘가 관리한 말 그대로 그래서 우리가 지금 사용하고 있는 이쪽에 저희가 만들어 놓은 스키마 이제 마이에스큐 시리즈는 접근할 수는 없지만...",
            "<09:36:18> 셀렉트 인서트 이 부분이 중요하지",
            "<09:40:27> 이렇게 프록시온에 그랜트 옵션을 줄 수 있는 슈퍼유저 이건 없지만, 기본적으로 사용자 계정은 지금 다 받아온 두 개는 루트만큼 내용을 지금",
            "<09:54:50> 데이터베이스 DB 수준 권한을 주고 싶어 그러면 그란트 하겠는데 셀렉트하고 인서트하고 ITB의 모든 것 가져다가 유저 호스트에다 권한에다가 주고 싶어 이렇게 간다는 거예요.",
            "<10:10:29> 전화를 뭔가를 조작할 수 있는 권한을 전혀 안 받았어.",
            "<10:30:10> 이렇게 해서 여기에 보면 얘가 지금 여기 그란트지 셀렉트 인서트 업데이트 딜리트 크레이트 드랍 릴로드 셧다운 프로세스 파일 요걸로 보던지 주는 거에 여기 있는 권한을 나열해서 줬는데...",
            "<11:05:11> 그리고 또 물어보면 해당 스키마가 가지고 있는 이 내용 하단에...",
            "<11:05:11> 올 프리빌리지 내용은 뭐야?",
            "<11:20:29> 몇개를 만들던 지금 상관은 없어요."
          ],
          "reasoning": "일부 중요한 내용을 강조하지만, 체계적이지 않고 반복적인 강조가 부족함. | 중요한 내용을 강조하는 표현이 부족하고, 동일한 톤으로 설명되고 있어 핵심 내용이 부각되지 않음. | 일부 중요한 내용을 강조하지만, 체계적이지 않음.",
          "confidence": 0.76,
          "caveats": []
        },
        {
          "item_id": "2.5",
          "item_name": "마무리 요약",
          "category": "2. 강의 도입 및 구조",
          "score": 1,
          "weight": "LOW",
          "evidence": [
            "<05:50:44> 여러분들 오늘 고생 많으셨습니다."
          ],
          "reasoning": "마무리 요약이 전혀 이루어지지 않고 강의가 갑자기 종료됨.",
          "confidence": 0.9,
          "caveats": []
        }
      ],
      "weighted_average": 3.0
    },
    {
      "category_name": "3. 개념 설명 명확성",
      "items": [
        {
          "item_id": "3.1",
          "item_name": "개념 정의",
          "category": "3. 개념 설명 명확성",
          "score": 2,
          "weight": "HIGH",
          "evidence": [
            "<09:11:07> 저희가 만약에 데이터베이스를 서버에 접속을 하려고 그러면 서버에 접속할 수 있는 계정을 먼저 생성하고...",
            "<09:22:05> 저 같은 경우에는 이 4개가 기본인데 여기 마이티비라는 애가 이 하나 있는 걸 볼 수 있어요.",
            "<09:31:15> 이렇게 들어온다는 거지 프로모스 그리고 여기에 IP를 주셔도 상관없고 자 그 다음에 여기까지는 와일드카드 여기 부분 사용할 수 있다고 했으니까",
            "<09:52:04> DBMS는 누구야 뭐 할 수 있어 이런 식으로 데이터가 계정 생성하고 권한 부여하고 객체에 접근할 수 있으니까 이 3단계가 누구야 뭐 할 수 있어 뭐 할 수 있어 이걸로 만드는 작업이다.",
            "<09:52:20> 어센디케이션은 누구야 이거니까 계정하고 비밀번호를 확인해야 되니까.",
            "<10:03:07> 그리고 나서 일단 제일 첫 번째 권한 부여를 한 거예랬냐면 마이 언더바 EMP의 모든 것만 접속할 수 있게끔 특정 데이터베이스에 대한 권한 부여를 했어요.",
            "<10:23:13> 다시 칼은 그냥 들어가는데 여기 보면 프롬호스트라는 게 있죠.",
            "<10:31:07> 명령 외우기가 조금 좋아 그리고 어 그렇지 그러면은 여기에서 나는 권한 추가를 하겠어",
            "<11:04:45> 해당 이제 대상 스키마를 주는 거지 그래서 나 마이 언더바 테스트에 모든 권한을 다 줄 거야.",
            "<11:19:24> 일단은 갈게요 사용자 권한 확인을 조금 더 한번 디테일하게 만들어 가지고..."
          ],
          "reasoning": "일부 개념은 정의 없이 사용되지만, 전체적으로 이해에 큰 문제는 없음. 예를 들어, '계정 생성'이나 '권한 부여'와 같은 용어는 설명 없이 사용됨. | 강의 중 여러 기술 용어와 개념이 등장하지만, 명확한 정의가 부족하여 수강생이 이해하기 어려울 수 있음. | 강의 중 여러 기술 용어가 등장하지만, 명확한 정의가 부족하여 수강생이 스스로 이해해야 하는 부분이 많음.",
          "confidence": 0.72,
          "caveats": [
            "STT 특성상 기술 용어 인식 오류 가능",
            "STT 특성상 스크립트 내용이 누락되었을 가능성 있음"
          ]
        },
        {
          "item_id": "3.2",
          "item_name": "비유 및 예시 활용",
          "category": "3. 개념 설명 명확성",
          "score": 2,
          "weight": "HIGH",
          "evidence": [
            "<09:19:12> 우리가 만약에 그 유즈 테스트 아니면 유즈 마이 EMP하고 DB 스키마를 만들잖아요.",
            "<09:25:21> 네트워크 개념이%를 살짝 주면 얘가 지금 현재 외부 어디에서나 접속 가능한 루트이다.",
            "<09:35:01> 얘는 지금 권한확인인데 그냥 권한 확인이 아니고 현재 로그인 권한 확인이에요.",
            "<09:52:10> 어센디케이션은 누구야 이거니까 계정하고 비밀번호를 확인해야 되니까.",
            "<09:55:23> 이 권한이 많으니까 권한이 많으니까 방금 전에 일단은 올라가서 쇼벤티스로 권한을 한번 보고 끝도 외우기 힘들어",
            "<10:08:04> 그래서 여기 유즈 마이 언더바 테스트를 했더니, 너 접근 권한이 없어 그래서 여기 에라 1044가 나와요.",
            "<10:23:43> 내 집에서 내 주소 부르진 않잖아.",
            "<10:36:36> 이거 하자마자 포 그란트 포 확인하고 밴드에서 바로 유즈 마이 테스트 했더니, 데이터베이스가 체인지드가 됐어",
            "<11:04:39> 권한 추가를 기존에 맨 처음에 생성할 때는 뉴 마이라고 하는 것에 마이 EMP만 줬었는데 지금은 다시 그란트나 올 전체 다 줄 거야.",
            "<11:19:12> 회사에서 전부 다 워크벤치를 쓴다고 생각하시면 안 돼..."
          ],
          "reasoning": "비유나 예시가 거의 없어 추상적 설명에 의존하고 있음. 실생활 예시나 비유가 부족하여 이해를 돕지 못함. | 일부 비유와 예시가 제공되지만, 빈도가 낮고 설명이 추상적임. | 비유나 실생활 예시가 거의 없어, 개념 설명이 추상적이고 이해하기 어려운 부분이 많음.",
          "confidence": 0.69,
          "caveats": [
            "STT 특성상 기술 용어 인식 오류 가능",
            "비유가 수강생에게 적절한지 여부는 추가적인 맥락 필요",
            "STT 특성상 문장 경계가 부정확할 수 있음",
            "STT 특성상 비유 및 예시의 누락 여부 확인이 어려움",
            "STT 특성상 문장 경계가 불명확할 수 있음"
          ]
        },
        {
          "item_id": "3.3",
          "item_name": "선행 개념 확인",
          "category": "3. 개념 설명 명확성",
          "score": 2,
          "weight": "MEDIUM",
          "evidence": [
            "<09:10:51> 오늘은 어제 사용자 개정 권한 저희 어제 살짝 내용 전체 확인하고...",
            "<09:24:00> 저희가 이제 마이나 U 해서 루트 그 다음에 P 해서 패스워드를 이렇게 넣고 가는데",
            "<09:31:47> 이 화면을 지금 현재 SQL 구문으로 지금 할 거기 때문에 계정 먼저 만들고 그 다음에기에 룰을 이용을 해서 프리빌리지를 받아야 된다는 거죠.",
            "<09:51:32> 살짝 되는 거지 이 섹션이",
            "<09:54:09> 자 그러면은 일단은 사용자 계정 권한은 어떤 할 수가 있어 권한은 프리빌리지라는 걸 할 수가 있는데,",
            "<10:10:04> 지금 칸트가 가지고 있는 프리빌리지를비 유즈 마이 EMP한테만 프리빌리지를 나는 전체 권한을 프리빌리지를 온 하겠는데 어디에만 권한을 준 거 레언더바 EMP의 스키마에만 준 거죠.",
            "<10:23:30> 내 집에서 내 주소 부르진 않잖아.",
            "<10:36:03> 플러쉬 프리빌리지스라는 게 적용이 돼서 지금 제가 이거 한 다음에 접속한 상태에서",
            "<11:03:07> 그 다음에 권한 확인하고 배정당 권한 확인하고 그다음에 로컬호스트가 내부 무한접속 그 다음에 얘는 외부 접속...",
            "<11:20:07> 가는 것이 지금 6단계니까 복습의 거 어차피 우리가 리보크까지 다 했으니까..."
          ],
          "reasoning": "대체로 선행 개념을 고려하며 설명하고 있으나, 일부 심화 내용으로의 점프가 있음. 예를 들어, '계정 인증 구조'에 대한 설명이 선행 개념 없이 진행됨. | 선행 개념에 대한 확인 없이 심화 내용으로 넘어가는 경향이 있어, 수강생이 따라가기 어려울 수 있음. | 가끔 선행 개념 없이 심화 내용으로 넘어가지만, 전체적으로 따라갈 수 있는 흐름이 있음.",
          "confidence": 0.67,
          "caveats": [
            "STT 특성상 문맥 파악이 어려울 수 있음",
            "STT 특성상 문장 경계가 부정확할 수 있음",
            "STT 특성상 문장 경계가 불명확할 수 있음",
            "STT 특성상 문맥이 불명확할 수 있음",
            "STT 특성상 스크립트 내용이 누락되었을 가능성 있음"
          ]
        },
        {
          "item_id": "3.4",
          "item_name": "발화 속도 적절성",
          "category": "3. 개념 설명 명확성",
          "score": 3,
          "weight": "MEDIUM",
          "evidence": [
            "<09:24:00> 저희가 이제 마이나 U 해서 루트 그 다음에 P 해서 패스워드를 이렇게 넣고 가는데...",
            "<09:30:07> 수업할 때는 뭐 그냥 내가 나 혼자 서버에 해서 실제 로컬 호스트를 돌린다고 생각하지",
            "<09:30:29> 혹시나 여러분들께 보시면서 화면을 전환했더니저블이 되죠.",
            "<09:54:28> 권한을 줄 수가 있고 여기에 그랜트라고 하는 이용을 해서 나 전체 누구한테 주겠다.",
            "<09:56:19> 때는 일단은 위에 내용은 그만하기로 하고 확인을 좀 해봅시다.",
            "<10:07:05> 일까은 기본이 뉴 언더바 유저는 로컬 호스트니까 얘는 그냥 이렇게 들어와 뉴 언더바 유저 이렇게 접속은 해봐야지 SQL 언더바 유 그 다음에 뉴 언더바 유저 마이너 P에서 패스워드 입력하고 그 다음에 살짜 들어옵니다.",
            "<10:24:33> 그리고 분리해 그래서 이렇게 유는 뉴 마이이고 호스트는 이거야.",
            "<10:39:00> 못 따라오신 분들은 여기까지는 하셔야 좀 재미가 있으니까",
            "<11:01:20> 자 저희가 이제 다시 한번 정리를 좀 해보면 쉬운데 쉬워요...",
            "<11:22:58> 마이너스 계정 다시 이제 확인하면 지금 이제 다 만들어 놓은 게%로 만들어 놓은 거 두 개..."
          ],
          "reasoning": "대체로 적절한 속도로 진행되며, 중요한 부분에서는 속도를 조절하고 있음. 그러나 가끔 빠르거나 느린 구간이 존재함. | 발화 속도가 일정하나, 때때로 빠르거나 느려 조절이 부족하여 집중에 방해가 될 수 있음. | 발화 속도가 일정하지만, 때때로 빠르거나 느려 조절이 부족한 부분이 있음.",
          "confidence": 0.72,
          "caveats": [
            "타임스탬프 간 발화량에 따라 속도 차이가 있을 수 있음",
            "STT 특성상 발화 속도 측정의 정확성에 한계가 있을 수 있음",
            "타임스탬프 간격으로 발화 밀도 추정",
            "STT 특성상 발화 속도 인식 오류 가능",
            "STT 특성상 발화 속도 측정의 정확성이 떨어질 수 있음"
          ]
        }
      ],
      "weighted_average": 2.2
    },
    {
      "category_name": "4. 예시 및 실습 연계",
      "items": [
        {
          "item_id": "4.1",
          "item_name": "예시 적절성",
          "category": "4. 예시 및 실습 연계",
          "score": 3,
          "weight": "HIGH",
          "evidence": [
            "<09:10:54> 99602dab: 계정 인증 구조가 있어요. 그래서 저희가 만약에 데이터베이스를 서버에 접속을 하려고 그러면 서버에 접속할 수 있는 계정을 먼저 생성하고 그 다음에 권한 부여받고 그 다음에 객체에 접근할 수 있는 이런 3단계가 있습니다.",
            "<09:25:05> 이게 내 PC에서는 내가 조끈 롤컬호스트니까 내 서버는 내가 내 PC에서 내가 이게 더 훨씬 권한이 높아 그런데 이제%를 주게 되면 이거는 외부 전체 네트워크 개념",
            "<09:31:47> 이 화면을 지금 현재 SQL 구문으로 지금 할 거기 때문에 계정 먼저 만들고...",
            "<09:54:20> 사용자 또는 역할이 어떤 작업을 어떤 작업을 할 수 있는지를 주는 거지...",
            "<09:54:09> 자 그러면은 일단은 사용자 계정 권한은 어떤 할 수가 있어 권한은 프리빌리지라는 걸 할 수가 있는데, 사용자 또는 역할이 어떤 작업을 어떤 작업을 할 수 있는지를 주는 거지",
            "<10:03:07> 그리고 나서 일단 제일 첫 번째 권한 부여를 한 거예랬냐면 마이 언더바 EMP의 모든 것만 접속할 수 있게끔 특정 데이터베이스에 대한 권한 부여를 했어요.",
            "<10:10:29> 전화를 뭔가를 조작할 수 있는 권한을 전혀 안 받았어.",
            "<10:23:13> 다시 칼은 그냥 들어가는데 여기 보면 프롬호스트라는 게 있죠.",
            "<10:29:25> 크리에이트 유저 알터 유저 이렇게 뉴유저의 로카 로스트에다가 일단은 뉴 패스워드 이렇게 하나 하고 뉴 테스트도 아까 뉴 테스트 했는데 뉴 1 2 3 확인하고",
            "<10:35:41> 그렇지 얘는 뼈은 재밌는 거고, 안되면 이상한 거니까 이렇게 사보자"
          ],
          "reasoning": "강의에서 계정 인증 구조를 설명하며 실제 데이터베이스 접근 시나리오를 제시하여 수강생들이 이해하기 쉽게 연결하고 있습니다. | 강의에서 로컬호스트와 외부 네트워크 개념을 설명하며, 실제 상황에서의 권한 차이를 예시로 들어 수강생들이 이해하기 쉽게 설명하고 있습니다. | 강의 중 SQL 구문을 사용하여 계정을 만드는 과정에 대한 설명이 있으나, 구체적인 실무 사례나 비유가 부족하여 수강생의 이해를 돕기에는 다소 부족함.",
          "confidence": 0.77,
          "caveats": [
            "스크립트 내용이 불완전하여 예시 적절성을 평가하기 어려움.",
            "강의 내용이 HTTP 통신 개요 및 웹 작동 방식임에도 불구하고, 관련된 예시가 전혀 제공되지 않음."
          ]
        },
        {
          "item_id": "4.2",
          "item_name": "실습 연계",
          "category": "4. 예시 및 실습 연계",
          "score": 4,
          "weight": "HIGH",
          "evidence": [
            "<09:12:01> 99602dab: 어제 열어놨던 여기 워크벤치 하나 열려있고 그 다음에 이제 도움말 제가 이렇게 하나 열어놓은 상태입니다.",
            "<09:12:17> 99602dab: 어제 했던 내용을 3번 가도록 할게요 저희가 사용자 권한 관리가 크리에이트 유저 그라이트 리버크 그 다음에 쇼 그랜트스 이렇게 돼서 이제 저희 익용 기본 명령이 있고...",
            "<09:31:47> 이 화면을 지금 현재 SQL 구문으로 지금 할 거기 때문에 계정 먼저 만들고 그 다음에기에 룰을 이용을 해서 프리빌리지를 받아야 된다는 거죠.",
            "<09:34:40> 권한 보게 여기가 어디냐면 지금 그냥 메인 하단계 제일 첫 번째 코드 올라오데 쇼그랜트스라고 하는 걸로 살짝...",
            "<09:54:35> 이런 식으로 접근하시면 되고요. 그다음에 데이터베이스 DB 수준 권한을 주고 싶어...",
            "<09:57:09> 나 생성 유저로 하겠어 그고 나서 유 유저에 로카호스트라는 걸로 하겠어 그 다음에 비밀번호는 뉴 패스워드로 하겠어 이런 식으로 하나 준다는 거지 이렇게 일단은 실행을 한번 해보면",
            "<10:05:01> 이렇게 해서 하나 구현하시면 돼요.",
            "<10:06:31> 그서 커맨드 열어서 ISQL의 마이나 U 뉴 유저 마이너 P로 일단 접속해보자 여기까지 하시고 천천히 현재 여기까지 하셨으면정 생성 권한 부여 권한 확인까지 하셨으면 나는 싫은데 여기 하나 더 킬 거야.",
            "<10:24:01> 잠깐만 있어봐요. 추가 확인했죠.",
            "<10:25:13> 들어오셔서 한번 넣고 천천히 하세요."
          ],
          "reasoning": "이론 설명 후 실습으로 자연스럽게 연결되며, 실습 내용이 이론과 관련되어 있습니다. 강사가 이전 수업 내용을 언급하며 실습을 진행하겠다고 명시적으로 언급하고 있습니다. | 이론 설명 후 SQL 구문을 사용하여 실습으로 자연스럽게 연결되며, 실습 내용이 이론과 관련되어 있습니다. | 이론 설명 후 실습으로 자연스럽게 연결되며, 실습 내용이 이론과 관련되어 있음. 실습 전환이 명확하게 이루어짐.",
          "confidence": 0.82,
          "caveats": [
            "이론 설명 후 실습으로의 자연스러운 연결이 전혀 없음.",
            "스크립트 내용이 불완전하여 실습 연계성을 평가하기 어려움."
          ]
        }
      ],
      "weighted_average": 3.5
    },
    {
      "category_name": "5. 수강생 상호작용",
      "items": [
        {
          "item_id": "5.1",
          "item_name": "오류 대응",
          "category": "5. 수강생 상호작용",
          "score": 3,
          "weight": "MEDIUM",
          "evidence": [
            "<09:35:01> 얘는 지금 권한확인인데 그냥 권한 확인이 아니고 현재 로그인 권한 확인이에요.",
            "<09:57:09> 나 생성 유저로 하겠어 그고 나서 유 유저에 로카호스트라는 걸로 하겠어",
            "<10:01:29> 되셨어요습니다. 잠깐",
            "<10:08:04> 그래서 여기 유즈 마이 언더바 테스트를 했더니, 너 접근 권한이 없어 그래서 여기 에라 1044가 나와요.",
            "<10:23:30> 그런데 실제 거기서 IP를 지정을 하게 되면 프로모스트가 해당 IP를 찾아서 접속하는 상태에 수신을 하기 때문에 실제 그냥 하시면 안 되고",
            "<10:24:00> 그렇게 접속하셔야 돼 거기다가 호스트라고 이렇게 하나 주셔야 마이에스켈이 가지고 있는 뉴마이에 호스트를 주시고 접근하셔야 된다.",
            "<11:14:30> 확인 들갔나 확인 이제 실행 한번 해보고 그 다음에 다시 한번 확인하면 없어져 이거 있어도 실행이 되는 거라고 빨간 거 있어도 실행이 되는 거니까 걱정하지 말고 하세요.",
            "<12:03:50> 여러분들 다 어디 갔다 오셨어요.",
            "<12:04:00> 갑자기 막 우두두두 다 나가시던데 저만 나갔어요.",
            "<01:24:04> 저희가 일반적으로 데이터 타입을 사용하는 것이 아니라 해당 속성에 대한 어트리뷰트 속성 정보를 J슨 타입으로 줘서 이렇게"
          ],
          "reasoning": "강의 중 오류 발생에 대한 언급이 없으므로, 오류 대응 여부를 평가할 수 없음. | 스크립트에서 오류 발생에 대한 언급이 없으므로, 오류 대응 여부를 평가할 수 없음. | 강사가 오류 발생 시 적절히 대응하고 있지만, 설명이 다소 간략하여 추가적인 디버깅 과정이나 학습 기회로 전환하는 부분이 부족함.",
          "confidence": 0.8,
          "caveats": [
            "STT 오류로 인해 일부 발언이 누락되었을 가능성 있음",
            "수강생의 발언이 강사로 잘못 인식될 가능성 있음",
            "일부 오류 상황에 대한 설명이 간략할 수 있음",
            "STT 오류로 인해 강사의 발언이 정확히 전달되지 않았을 가능성 있음",
            "실습 중 오류가 발생하지 않았을 가능성 있음"
          ]
        },
        {
          "item_id": "5.2",
          "item_name": "이해 확인 질문",
          "category": "5. 수강생 상호작용",
          "score": 3,
          "weight": "HIGH",
          "evidence": [
            "<09:12:01> 어제 했던 내용을 3번 가도록 할게요",
            "<09:16:12> 혹시 기억나실까요?",
            "<09:30:29> 혹시나 여러분들께 보시면서 화면을 전환했더니 저블이 되죠.",
            "<09:37:31> 혹시 기억하실까요?",
            "<09:39:14> 여러분들 거 갖고 계시면 유저 프리빌리지의 저는 지금 마이디비의 프로모스트를 지금 퍼로 지금 바꾼 상태잖아요.",
            "<09:46:17> 이해 가능",
            "<09:47:23> 되셨어요.",
            "<10:01:29> 되셨어요습니다. 잠깐",
            "<10:04:51> 이해는 안 했나 보다 이렇게 이 테스트 여기서 두 가지 다 해보세요.",
            "<10:05:01> 이해는 안 했나 보다 이렇게 이 테스트 여기서 두 가지 다 해보세요."
          ],
          "reasoning": "이해 확인 질문이 있으나 빈도가 낮고 형식적임. 주요 개념 설명 후 이해 여부를 확인하는 질문이 부족함. | 이해 확인 질문이 있으나 빈도가 낮고 형식적임. 추가적인 질문이 필요함. | 주요 개념 설명 후 이해 확인 질문을 자주 하며, 수강생의 이해도를 점검하는 질문을 활용하고 있음.",
          "confidence": 0.81,
          "caveats": [
            "화자 구분 부정확으로 일부 확인 질문 누락 가능",
            "질문이 수강생의 이해도를 깊이 있게 점검하지 못할 가능성",
            "일부 질문이 수강생의 이해도를 깊이 있게 점검하지 못할 가능성",
            "스크립트가 짧아 이해 확인 질문 여부를 판단하기 어려움",
            "화자 구분 부정확으로 일부 질문 누락 가능"
          ]
        },
        {
          "item_id": "5.3",
          "item_name": "참여 유도",
          "category": "5. 수강생 상호작용",
          "score": 3,
          "weight": "HIGH",
          "evidence": [
            "<09:39:32> 그런데 만약에 사사님은 여기에 지금 내가 만든 계정에 여기 프로모스트가 로컬 호스트야가 뒤에가 그리고 내가 여기다가 불을 주고 글로벌 풀리빌리지를 지금 받은 상태야 이렇게 해서 생각한다면.",
            "<09:47:49> 이렇게 얘만 보지 말고 이렇게",
            "<09:48:11> 여기에 지금 유저 세션하고 여기 보면 시스 있었죠.",
            "<09:56:19> 확인을 좀 해봅시다",
            "<10:04:32> 여러분들 지금 여기까지 권한 설정을 했었는데 여기에서 지금 얘 하나 지금 이거 뉴언더바 테스트도 지금 하셨을 거 만들어놓은 거 여기도 확인하세요.",
            "<10:01:38> 쉬셨으면 저는 여기서 권한 부여를 여기다가 권한 확인을 한번 해봐요.",
            "<10:04:32> 여러분들 지금 여기까지 권한 설정을 했었는데 여기에서 지금 얘 하나 지금 이거 뉴언더바 테스트도 지금 하셨을 거 만들어놓은 거 여기도 확인하세요.",
            "<10:24:23> CMD 창 하나 아니면 다른 곳에서 접속 그러 이렇게 되는 거지",
            "<10:25:13> 들어오셔서 한번 넣고 천천히 하세요.",
            "<11:14:04> 한번 해보시면 여러분 지금 오른쪽은 약간쪽로 와야 돼요."
          ],
          "reasoning": "대부분 일방적 설명으로 수강생 참여 유도가 거의 없음. 참여를 유도하는 표현이 부족함. | 대부분 일방적 설명으로, 수강생 참여 유도가 거의 없음. | 수강생 참여를 유도하는 발언이 있으나, 빈도가 낮고 형식적인 질문이 많아 실질적인 참여 유도가 부족함.",
          "confidence": 0.78,
          "caveats": [
            "수강생 참여 유도 표현이 부족함",
            "일부 참여 유도 발언이 STT 오류로 인해 누락될 가능성 있음",
            "일부 참여 유도 표현이 다소 형식적일 수 있음",
            "STT 오류로 인해 수강생의 반응이 정확히 기록되지 않았을 가능성 있음",
            "참여 유도 표현이 명확하지 않을 수 있음"
          ]
        },
        {
          "item_id": "5.4",
          "item_name": "질문 응답 충분성",
          "category": "5. 수강생 상호작용",
          "score": 3,
          "weight": "HIGH",
          "evidence": [
            "<09:35:17> 내가 지금 현재 여기 루트로 로컬호스트가 지금 되어 있죠.",
            "<09:40:38> 이렇게 프록시온에 그랜트 옵션을 줄 수 있는 슈퍼유저 이건 없지만.",
            "<09:54:20> 그래서 이거 하려고 그러면 보통 크리에이트 권한 전체 권한이 크리에이트 유저 셧다운 파일 릴로드 프로세스 슈퍼 이렇게 해서 접근 권한을 줄 수가 있고",
            "<10:01:29> 되셨어요습니다. 잠깐",
            "<10:04:51> 이해는 안 했나 보다 이렇게 이 테스트 여기서 두 가지 다 해보세요.",
            "<10:08:11> 그고 나서 유즈에서 마이 언더바 EMP 했더니, 얘는 데이터베이스 체인지드가 되는 거예요.",
            "<10:24:00> 그렇게 접속하셔야 돼 거기다가 호스트라고 이렇게 하나 주셔야 마이에스켈이 가지고 있는 뉴마이에 호스트를 주시고 접근하셔야 된다.",
            "<11:04:39> 권한 추가를 기존에 맨 처음에 생성할 때는 뉴 마이라고 하는 것에 마이 EMP만 줬었는데 지금은 다시 그란트나 올 전체 다 줄 거야.",
            "<11:23:39> 자 그 다음에 딱 내려가서 권한이 없으니까 권한을 지정을 해 올 프리빌리지 온 투 나 마이 샘플에다가 다 줄 거야.",
            "<01:25:14> 이렇게 그렇죠. 사용자 정보를 그냥 저장하는 용도로 볼 수 있습니다."
          ],
          "reasoning": "수강생 질문에 대한 응답이 관찰되지 않아 질문 응답의 충분성을 평가할 수 없음. | 질문에 대한 응답이 부족하거나 주제에서 벗어난 경우가 있음. | 수강생 질문에 대해 명확하고 충분한 답변을 제공하며, 관련 배경 지식도 함께 설명하고 있음.",
          "confidence": 0.76,
          "caveats": [
            "STT 오류로 인해 질문 응답 내용이 불완전할 수 있음",
            "답변의 구체성이 부족하여 수강생의 이해를 돕지 못할 가능성",
            "질문에 대한 구체적인 응답이 부족할 수 있음",
            "수강생 질문이 관찰되지 않아 평가가 제한적임",
            "수강생 질문이 없었을 가능성 있음"
          ]
        }
      ],
      "weighted_average": 3.0
    }
  ],
  "weighted_average": 2.933333333333333,
  "weighted_total": 132.0,
  "category_averages": {
    "1. 언어 표현 품질": 3.2857142857142856,
    "2. 강의 도입 및 구조": 3.0,
    "3. 개념 설명 명확성": 2.2,
    "4. 예시 및 실습 연계": 3.5,
    "5. 수강생 상호작용": 3.0
  },
  "category_scores": {
    "1. 언어 표현 품질": [
      {
        "item_id": "1.1",
        "item_name": "불필요한 반복 표현",
        "category": "1. 언어 표현 품질",
        "score": 3,
        "weight": "HIGH",
        "evidence": [
          "<09:10:51> ... 저희 어제 살짝 내용 전체 확인하고 그 다음에 저희 오늘 이어서 진행을 할 거고요.",
          "<09:11:07> ... 저희가 만약에 데이터베이스를 서버에 접속을 하려고 그러면 ...",
          "<09:11:24> ... 그 다음에 권한을 설정을 하고 권한을 삭제를 하는 ...",
          "<09:20:37> ... 그래서 ...",
          "<09:22:36> ... 저희는 실제 루트가 가장 높다는 거죠 ...",
          "<09:30:07> ... 이렇게 접속이 가능해가죠 수업할 때는 ...",
          "<09:30:39> ... 이제 ...",
          "<09:31:47> ... 자 ...",
          "<09:31:58> ... 다시 옵니다 ...",
          "<09:41:47> ... 이제 얘네가 가지고 있는 기본 정보들은 다 확인을 했고 ..."
        ],
        "reasoning": "습관적 표현 '저희'가 여러 번 반복되며, '그 다음에'와 같은 연결어도 빈번하게 사용됨. 분당 약 4회 관찰됨. | 습관적 표현 '그래서'와 '저희'가 여러 차례 반복되어 나타나며, 특히 '그래서'는 분당 약 3회 관찰됨. 강의 흐름에 큰 문제는 없으나 반복이 눈에 띔. | 습관적 표현 '이제'와 '자'가 해당 구간에서 각각 3회 관찰됨. 반복이 있지만 내용 전달에 큰 문제는 없음.",
        "confidence": 0.78,
        "caveats": [
          "STT 오인식으로 인한 반복 가능성 일부 존재"
        ]
      },
      {
        "item_id": "1.2",
        "item_name": "발화 완결성",
        "category": "1. 언어 표현 품질",
        "score": 3,
        "weight": "MEDIUM",
        "evidence": [
          "<09:11:10> ... 그 다음에 권한 부여받고 그 다음에 객체에 접근할 수 있는 이런 3단계가 있습니다.",
          "<09:11:37> ... 끝나면 그 다음에 트리거 이용을 해서 어떤 식으로 데이터가 자동 실행을 한꺼번에 할 수 있는지를 확인해 보도록 할게요.",
          "<09:20:37> ... 그래서 우리가 지금 사용하고 있는 이쪽에 저희가 만들어 놓은 스키마 이제 마이에스큐 시리즈는 접근할 수는 없지만 ...",
          "<09:30:07> ... 이렇게 접속이 가능해가죠 수업할 때는 ...",
          "<09:31:51> ... 거죠. 이 수업을 ...",
          "<09:32:40> ... 이렇게 해서 하나 둘 넷 다섯 개의 큰 섹션으로 나눠져 있고 ...",
          "<09:40:38> ... 이건 없지만, 기본적으로 사용자 계정은 지금 다 받아온 두 개는 루트만큼 내용을 지금 ...",
          "<09:54:20> ... 작업을 할 수 있는지를 주는 거지 ...",
          "<09:50:31> ... 그래서 여기 이제 유저 테이블에 있는 애들 ...",
          "<09:52:20> ... 생각하시면 조금 편해요 ..."
        ],
        "reasoning": "비완결 문장이 간간이 나타나며, 특히 긴 문장에서 중간에 끊기는 경우가 있어 의미 파악이 어려운 부분이 있음. | 비완결 문장이 간간이 나타나며, 특히 긴 문장에서 주어와 서술어가 명확하지 않은 경우가 있음. 수강생이 의미를 추론해야 하는 경우가 발생. | 비완결 문장이 간간이 나타나며, 특히 문장 중간에 주제가 전환되는 경우가 있어 의미 파악이 어려운 부분이 있음.",
        "confidence": 0.72,
        "caveats": [
          "STT 오류로 인한 문장 끊김 가능성",
          "STT 오류로 인한 문장 끊김은 감점 대상에서 제외"
        ]
      },
      {
        "item_id": "1.3",
        "item_name": "언어 일관성",
        "category": "1. 언어 표현 품질",
        "score": 4,
        "weight": "MEDIUM",
        "evidence": [
          "<09:10:27> ... 안녕하세요. 오늘 수업 진행하도록 하겠습니다.",
          "<09:10:38> ... 저희 어제는 인덱스 구현해서 개념하고 필요성 진행하는 걸 사용을 했었고 ...",
          "<09:20:37> ... 저희가 지금 사용하고 있는 ...",
          "<09:22:36> ... 저희는 실제 루트가 가장 높다는 거죠 ...",
          "<09:30:29> ... 여러분들께 ...",
          "<09:31:47> ... 자 얘네들은 ...",
          "<09:40:38> ... 이렇게 프록시온에 그랜트 옵션을 줄 수 있는 슈퍼유저 ...",
          "<09:52:20> ... 어센디케이션은 누구야 이거니까 계정하고 비밀번호를 확인해야 되니까.",
          "<09:50:31> ... 저희가 ...",
          "<09:51:20> ... 저희가 ..."
        ],
        "reasoning": "대체로 존댓말로 일관되지만, 특정 구간에서 반말이 혼용되는 경향이 있어 약간의 어색함이 존재함. | 대체로 존댓말로 일관되지만, 특정 구간에서 반말이 혼용되는 경향이 있음. 전반적으로는 일관성이 유지되고 있음. | 대체로 존댓말로 일관되지만, 특정 구간에서 반말이 혼용되어 어색함이 느껴짐.",
        "confidence": 0.81,
        "caveats": [
          "수강생과 대화 시 톤 변화는 자연스러운 것으로 봄"
        ]
      }
    ],
    "2. 강의 도입 및 구조": [
      {
        "item_id": "2.1",
        "item_name": "학습 목표 안내",
        "category": "2. 강의 도입 및 구조",
        "score": 4,
        "weight": "HIGH",
        "evidence": [
          "<09:10:27> 오늘 수업 진행하도록 하겠습니다.",
          "<09:10:38> 오늘은 어제 사용자 개정 권한 저희 어제 살짝 내용 전체 확인하고 그 다음에 저희 오늘 이어서 진행을 할 거고요."
        ],
        "reasoning": "강의 시작 후 1분 이내에 학습 목표를 언급하고 진행 순서를 설명함. '오늘은 어제 사용자 개정 권한...' 부분에서 오늘의 주제를 명확히 제시함.",
        "confidence": 0.85,
        "caveats": []
      },
      {
        "item_id": "2.2",
        "item_name": "전날 복습 연계",
        "category": "2. 강의 도입 및 구조",
        "score": 4,
        "weight": "HIGH",
        "evidence": [
          "<09:10:38> 어제는 인덱스 구현해서 개념하고 필요성 진행하는 걸 사용을 했었고...",
          "<09:10:51> 오늘은 어제 사용자 개정 권한 저희 어제 살짝 내용 전체 확인하고..."
        ],
        "reasoning": "이전 강의 내용을 간략히 언급하며 오늘 내용으로 자연스럽게 전환함. '어제는 인덱스 구현...' 부분에서 복습을 잘 연결함.",
        "confidence": 0.85,
        "caveats": []
      },
      {
        "item_id": "2.3",
        "item_name": "설명 순서",
        "category": "2. 강의 도입 및 구조",
        "score": 2,
        "weight": "MEDIUM",
        "evidence": [
          "<09:11:07> 저희가 만약에 데이터베이스를 서버에 접속을 하려고 그러면 서버에 접속할 수 있는 계정을 먼저 생성하고...",
          "<09:20:37> 걔를 그 뷰의 객체를 얘가 관리한 말 그대로 그래서 우리가 지금 사용하고 있는 이쪽에 저희가 만들어 놓은 스키마 이제 마이에스큐 시리즈는 접근할 수는 없지만...",
          "<09:35:01> 얘는 지금 권한확인인데 그냥 권한 확인이 아니고 현재 로그인 권한 확인이에요.",
          "<09:40:27> 이렇게 프록시온에 그랜트 옵션을 줄 수 있는 슈퍼유저 이건 없지만, 기본적으로 사용자 계정은 지금 다 받아온 두 개는 루트만큼 내용을 지금",
          "<09:54:09> 자 그러면은 일단은 사용자 계정 권한은 어떤 할 수가 있어 권한은 프리빌리지라는 걸 할 수가 있는데, 사용자 또는 역할이 어떤 작업을 어떤 작업을 할 수 있는지를 주는 거지",
          "<10:10:29> 전화를 뭔가를 조작할 수 있는 권한을 전혀 안 받았어.",
          "<10:29:25> 크리에이트 유저 알터 유저 이렇게 뉴유저의 로카 로스트에다가 일단은 뉴 패스워드 이렇게 하나 하고 뉴 테스트도 아까 뉴 테스트 했는데 뉴 1 2 3 확인하고...",
          "<11:01:20> 자 저희가 이제 다시 한번 정리를 좀 해보면 쉬운데 쉬워요...",
          "<11:04:06> 그래서 서버에 어떤 계정이 있는지 한번 확인해 보고 싶다.",
          "<11:20:29> 몇개를 만들던 지금 상관은 없어요."
        ],
        "reasoning": "개념 설명 후 예시를 제시하는 구조는 있지만, 때때로 순서가 뒤바뀌거나 단계가 생략되는 경향이 있음. | 개념, 예시, 실습의 순서가 혼재되어 있으며, 설명이 구조적으로 제시되지 않음. | 개념과 예시가 혼재되어 있지만, 대체로 설명 순서가 유지되고 있음.",
        "confidence": 0.78,
        "caveats": []
      },
      {
        "item_id": "2.4",
        "item_name": "핵심 내용 강조",
        "category": "2. 강의 도입 및 구조",
        "score": 2,
        "weight": "MEDIUM",
        "evidence": [
          "<09:15:38> 사용자 생성 이런 모든 제어가 가능한 게 루트 저희가 맨 처음에 수업을 할 때 루뜨로 왔단 말이야.",
          "<09:20:37> 걔를 그 뷰의 객체를 얘가 관리한 말 그대로 그래서 우리가 지금 사용하고 있는 이쪽에 저희가 만들어 놓은 스키마 이제 마이에스큐 시리즈는 접근할 수는 없지만...",
          "<09:36:18> 셀렉트 인서트 이 부분이 중요하지",
          "<09:40:27> 이렇게 프록시온에 그랜트 옵션을 줄 수 있는 슈퍼유저 이건 없지만, 기본적으로 사용자 계정은 지금 다 받아온 두 개는 루트만큼 내용을 지금",
          "<09:54:50> 데이터베이스 DB 수준 권한을 주고 싶어 그러면 그란트 하겠는데 셀렉트하고 인서트하고 ITB의 모든 것 가져다가 유저 호스트에다 권한에다가 주고 싶어 이렇게 간다는 거예요.",
          "<10:10:29> 전화를 뭔가를 조작할 수 있는 권한을 전혀 안 받았어.",
          "<10:30:10> 이렇게 해서 여기에 보면 얘가 지금 여기 그란트지 셀렉트 인서트 업데이트 딜리트 크레이트 드랍 릴로드 셧다운 프로세스 파일 요걸로 보던지 주는 거에 여기 있는 권한을 나열해서 줬는데...",
          "<11:05:11> 그리고 또 물어보면 해당 스키마가 가지고 있는 이 내용 하단에...",
          "<11:05:11> 올 프리빌리지 내용은 뭐야?",
          "<11:20:29> 몇개를 만들던 지금 상관은 없어요."
        ],
        "reasoning": "일부 중요한 내용을 강조하지만, 체계적이지 않고 반복적인 강조가 부족함. | 중요한 내용을 강조하는 표현이 부족하고, 동일한 톤으로 설명되고 있어 핵심 내용이 부각되지 않음. | 일부 중요한 내용을 강조하지만, 체계적이지 않음.",
        "confidence": 0.76,
        "caveats": []
      },
      {
        "item_id": "2.5",
        "item_name": "마무리 요약",
        "category": "2. 강의 도입 및 구조",
        "score": 1,
        "weight": "LOW",
        "evidence": [
          "<05:50:44> 여러분들 오늘 고생 많으셨습니다."
        ],
        "reasoning": "마무리 요약이 전혀 이루어지지 않고 강의가 갑자기 종료됨.",
        "confidence": 0.9,
        "caveats": []
      }
    ],
    "3. 개념 설명 명확성": [
      {
        "item_id": "3.1",
        "item_name": "개념 정의",
        "category": "3. 개념 설명 명확성",
        "score": 2,
        "weight": "HIGH",
        "evidence": [
          "<09:11:07> 저희가 만약에 데이터베이스를 서버에 접속을 하려고 그러면 서버에 접속할 수 있는 계정을 먼저 생성하고...",
          "<09:22:05> 저 같은 경우에는 이 4개가 기본인데 여기 마이티비라는 애가 이 하나 있는 걸 볼 수 있어요.",
          "<09:31:15> 이렇게 들어온다는 거지 프로모스 그리고 여기에 IP를 주셔도 상관없고 자 그 다음에 여기까지는 와일드카드 여기 부분 사용할 수 있다고 했으니까",
          "<09:52:04> DBMS는 누구야 뭐 할 수 있어 이런 식으로 데이터가 계정 생성하고 권한 부여하고 객체에 접근할 수 있으니까 이 3단계가 누구야 뭐 할 수 있어 뭐 할 수 있어 이걸로 만드는 작업이다.",
          "<09:52:20> 어센디케이션은 누구야 이거니까 계정하고 비밀번호를 확인해야 되니까.",
          "<10:03:07> 그리고 나서 일단 제일 첫 번째 권한 부여를 한 거예랬냐면 마이 언더바 EMP의 모든 것만 접속할 수 있게끔 특정 데이터베이스에 대한 권한 부여를 했어요.",
          "<10:23:13> 다시 칼은 그냥 들어가는데 여기 보면 프롬호스트라는 게 있죠.",
          "<10:31:07> 명령 외우기가 조금 좋아 그리고 어 그렇지 그러면은 여기에서 나는 권한 추가를 하겠어",
          "<11:04:45> 해당 이제 대상 스키마를 주는 거지 그래서 나 마이 언더바 테스트에 모든 권한을 다 줄 거야.",
          "<11:19:24> 일단은 갈게요 사용자 권한 확인을 조금 더 한번 디테일하게 만들어 가지고..."
        ],
        "reasoning": "일부 개념은 정의 없이 사용되지만, 전체적으로 이해에 큰 문제는 없음. 예를 들어, '계정 생성'이나 '권한 부여'와 같은 용어는 설명 없이 사용됨. | 강의 중 여러 기술 용어와 개념이 등장하지만, 명확한 정의가 부족하여 수강생이 이해하기 어려울 수 있음. | 강의 중 여러 기술 용어가 등장하지만, 명확한 정의가 부족하여 수강생이 스스로 이해해야 하는 부분이 많음.",
        "confidence": 0.72,
        "caveats": [
          "STT 특성상 기술 용어 인식 오류 가능",
          "STT 특성상 스크립트 내용이 누락되었을 가능성 있음"
        ]
      },
      {
        "item_id": "3.2",
        "item_name": "비유 및 예시 활용",
        "category": "3. 개념 설명 명확성",
        "score": 2,
        "weight": "HIGH",
        "evidence": [
          "<09:19:12> 우리가 만약에 그 유즈 테스트 아니면 유즈 마이 EMP하고 DB 스키마를 만들잖아요.",
          "<09:25:21> 네트워크 개념이%를 살짝 주면 얘가 지금 현재 외부 어디에서나 접속 가능한 루트이다.",
          "<09:35:01> 얘는 지금 권한확인인데 그냥 권한 확인이 아니고 현재 로그인 권한 확인이에요.",
          "<09:52:10> 어센디케이션은 누구야 이거니까 계정하고 비밀번호를 확인해야 되니까.",
          "<09:55:23> 이 권한이 많으니까 권한이 많으니까 방금 전에 일단은 올라가서 쇼벤티스로 권한을 한번 보고 끝도 외우기 힘들어",
          "<10:08:04> 그래서 여기 유즈 마이 언더바 테스트를 했더니, 너 접근 권한이 없어 그래서 여기 에라 1044가 나와요.",
          "<10:23:43> 내 집에서 내 주소 부르진 않잖아.",
          "<10:36:36> 이거 하자마자 포 그란트 포 확인하고 밴드에서 바로 유즈 마이 테스트 했더니, 데이터베이스가 체인지드가 됐어",
          "<11:04:39> 권한 추가를 기존에 맨 처음에 생성할 때는 뉴 마이라고 하는 것에 마이 EMP만 줬었는데 지금은 다시 그란트나 올 전체 다 줄 거야.",
          "<11:19:12> 회사에서 전부 다 워크벤치를 쓴다고 생각하시면 안 돼..."
        ],
        "reasoning": "비유나 예시가 거의 없어 추상적 설명에 의존하고 있음. 실생활 예시나 비유가 부족하여 이해를 돕지 못함. | 일부 비유와 예시가 제공되지만, 빈도가 낮고 설명이 추상적임. | 비유나 실생활 예시가 거의 없어, 개념 설명이 추상적이고 이해하기 어려운 부분이 많음.",
        "confidence": 0.69,
        "caveats": [
          "STT 특성상 기술 용어 인식 오류 가능",
          "비유가 수강생에게 적절한지 여부는 추가적인 맥락 필요",
          "STT 특성상 문장 경계가 부정확할 수 있음",
          "STT 특성상 비유 및 예시의 누락 여부 확인이 어려움",
          "STT 특성상 문장 경계가 불명확할 수 있음"
        ]
      },
      {
        "item_id": "3.3",
        "item_name": "선행 개념 확인",
        "category": "3. 개념 설명 명확성",
        "score": 2,
        "weight": "MEDIUM",
        "evidence": [
          "<09:10:51> 오늘은 어제 사용자 개정 권한 저희 어제 살짝 내용 전체 확인하고...",
          "<09:24:00> 저희가 이제 마이나 U 해서 루트 그 다음에 P 해서 패스워드를 이렇게 넣고 가는데",
          "<09:31:47> 이 화면을 지금 현재 SQL 구문으로 지금 할 거기 때문에 계정 먼저 만들고 그 다음에기에 룰을 이용을 해서 프리빌리지를 받아야 된다는 거죠.",
          "<09:51:32> 살짝 되는 거지 이 섹션이",
          "<09:54:09> 자 그러면은 일단은 사용자 계정 권한은 어떤 할 수가 있어 권한은 프리빌리지라는 걸 할 수가 있는데,",
          "<10:10:04> 지금 칸트가 가지고 있는 프리빌리지를비 유즈 마이 EMP한테만 프리빌리지를 나는 전체 권한을 프리빌리지를 온 하겠는데 어디에만 권한을 준 거 레언더바 EMP의 스키마에만 준 거죠.",
          "<10:23:30> 내 집에서 내 주소 부르진 않잖아.",
          "<10:36:03> 플러쉬 프리빌리지스라는 게 적용이 돼서 지금 제가 이거 한 다음에 접속한 상태에서",
          "<11:03:07> 그 다음에 권한 확인하고 배정당 권한 확인하고 그다음에 로컬호스트가 내부 무한접속 그 다음에 얘는 외부 접속...",
          "<11:20:07> 가는 것이 지금 6단계니까 복습의 거 어차피 우리가 리보크까지 다 했으니까..."
        ],
        "reasoning": "대체로 선행 개념을 고려하며 설명하고 있으나, 일부 심화 내용으로의 점프가 있음. 예를 들어, '계정 인증 구조'에 대한 설명이 선행 개념 없이 진행됨. | 선행 개념에 대한 확인 없이 심화 내용으로 넘어가는 경향이 있어, 수강생이 따라가기 어려울 수 있음. | 가끔 선행 개념 없이 심화 내용으로 넘어가지만, 전체적으로 따라갈 수 있는 흐름이 있음.",
        "confidence": 0.67,
        "caveats": [
          "STT 특성상 문맥 파악이 어려울 수 있음",
          "STT 특성상 문장 경계가 부정확할 수 있음",
          "STT 특성상 문장 경계가 불명확할 수 있음",
          "STT 특성상 문맥이 불명확할 수 있음",
          "STT 특성상 스크립트 내용이 누락되었을 가능성 있음"
        ]
      },
      {
        "item_id": "3.4",
        "item_name": "발화 속도 적절성",
        "category": "3. 개념 설명 명확성",
        "score": 3,
        "weight": "MEDIUM",
        "evidence": [
          "<09:24:00> 저희가 이제 마이나 U 해서 루트 그 다음에 P 해서 패스워드를 이렇게 넣고 가는데...",
          "<09:30:07> 수업할 때는 뭐 그냥 내가 나 혼자 서버에 해서 실제 로컬 호스트를 돌린다고 생각하지",
          "<09:30:29> 혹시나 여러분들께 보시면서 화면을 전환했더니저블이 되죠.",
          "<09:54:28> 권한을 줄 수가 있고 여기에 그랜트라고 하는 이용을 해서 나 전체 누구한테 주겠다.",
          "<09:56:19> 때는 일단은 위에 내용은 그만하기로 하고 확인을 좀 해봅시다.",
          "<10:07:05> 일까은 기본이 뉴 언더바 유저는 로컬 호스트니까 얘는 그냥 이렇게 들어와 뉴 언더바 유저 이렇게 접속은 해봐야지 SQL 언더바 유 그 다음에 뉴 언더바 유저 마이너 P에서 패스워드 입력하고 그 다음에 살짜 들어옵니다.",
          "<10:24:33> 그리고 분리해 그래서 이렇게 유는 뉴 마이이고 호스트는 이거야.",
          "<10:39:00> 못 따라오신 분들은 여기까지는 하셔야 좀 재미가 있으니까",
          "<11:01:20> 자 저희가 이제 다시 한번 정리를 좀 해보면 쉬운데 쉬워요...",
          "<11:22:58> 마이너스 계정 다시 이제 확인하면 지금 이제 다 만들어 놓은 게%로 만들어 놓은 거 두 개..."
        ],
        "reasoning": "대체로 적절한 속도로 진행되며, 중요한 부분에서는 속도를 조절하고 있음. 그러나 가끔 빠르거나 느린 구간이 존재함. | 발화 속도가 일정하나, 때때로 빠르거나 느려 조절이 부족하여 집중에 방해가 될 수 있음. | 발화 속도가 일정하지만, 때때로 빠르거나 느려 조절이 부족한 부분이 있음.",
        "confidence": 0.72,
        "caveats": [
          "타임스탬프 간 발화량에 따라 속도 차이가 있을 수 있음",
          "STT 특성상 발화 속도 측정의 정확성에 한계가 있을 수 있음",
          "타임스탬프 간격으로 발화 밀도 추정",
          "STT 특성상 발화 속도 인식 오류 가능",
          "STT 특성상 발화 속도 측정의 정확성이 떨어질 수 있음"
        ]
      }
    ],
    "4. 예시 및 실습 연계": [
      {
        "item_id": "4.1",
        "item_name": "예시 적절성",
        "category": "4. 예시 및 실습 연계",
        "score": 3,
        "weight": "HIGH",
        "evidence": [
          "<09:10:54> 99602dab: 계정 인증 구조가 있어요. 그래서 저희가 만약에 데이터베이스를 서버에 접속을 하려고 그러면 서버에 접속할 수 있는 계정을 먼저 생성하고 그 다음에 권한 부여받고 그 다음에 객체에 접근할 수 있는 이런 3단계가 있습니다.",
          "<09:25:05> 이게 내 PC에서는 내가 조끈 롤컬호스트니까 내 서버는 내가 내 PC에서 내가 이게 더 훨씬 권한이 높아 그런데 이제%를 주게 되면 이거는 외부 전체 네트워크 개념",
          "<09:31:47> 이 화면을 지금 현재 SQL 구문으로 지금 할 거기 때문에 계정 먼저 만들고...",
          "<09:54:20> 사용자 또는 역할이 어떤 작업을 어떤 작업을 할 수 있는지를 주는 거지...",
          "<09:54:09> 자 그러면은 일단은 사용자 계정 권한은 어떤 할 수가 있어 권한은 프리빌리지라는 걸 할 수가 있는데, 사용자 또는 역할이 어떤 작업을 어떤 작업을 할 수 있는지를 주는 거지",
          "<10:03:07> 그리고 나서 일단 제일 첫 번째 권한 부여를 한 거예랬냐면 마이 언더바 EMP의 모든 것만 접속할 수 있게끔 특정 데이터베이스에 대한 권한 부여를 했어요.",
          "<10:10:29> 전화를 뭔가를 조작할 수 있는 권한을 전혀 안 받았어.",
          "<10:23:13> 다시 칼은 그냥 들어가는데 여기 보면 프롬호스트라는 게 있죠.",
          "<10:29:25> 크리에이트 유저 알터 유저 이렇게 뉴유저의 로카 로스트에다가 일단은 뉴 패스워드 이렇게 하나 하고 뉴 테스트도 아까 뉴 테스트 했는데 뉴 1 2 3 확인하고",
          "<10:35:41> 그렇지 얘는 뼈은 재밌는 거고, 안되면 이상한 거니까 이렇게 사보자"
        ],
        "reasoning": "강의에서 계정 인증 구조를 설명하며 실제 데이터베이스 접근 시나리오를 제시하여 수강생들이 이해하기 쉽게 연결하고 있습니다. | 강의에서 로컬호스트와 외부 네트워크 개념을 설명하며, 실제 상황에서의 권한 차이를 예시로 들어 수강생들이 이해하기 쉽게 설명하고 있습니다. | 강의 중 SQL 구문을 사용하여 계정을 만드는 과정에 대한 설명이 있으나, 구체적인 실무 사례나 비유가 부족하여 수강생의 이해를 돕기에는 다소 부족함.",
        "confidence": 0.77,
        "caveats": [
          "스크립트 내용이 불완전하여 예시 적절성을 평가하기 어려움.",
          "강의 내용이 HTTP 통신 개요 및 웹 작동 방식임에도 불구하고, 관련된 예시가 전혀 제공되지 않음."
        ]
      },
      {
        "item_id": "4.2",
        "item_name": "실습 연계",
        "category": "4. 예시 및 실습 연계",
        "score": 4,
        "weight": "HIGH",
        "evidence": [
          "<09:12:01> 99602dab: 어제 열어놨던 여기 워크벤치 하나 열려있고 그 다음에 이제 도움말 제가 이렇게 하나 열어놓은 상태입니다.",
          "<09:12:17> 99602dab: 어제 했던 내용을 3번 가도록 할게요 저희가 사용자 권한 관리가 크리에이트 유저 그라이트 리버크 그 다음에 쇼 그랜트스 이렇게 돼서 이제 저희 익용 기본 명령이 있고...",
          "<09:31:47> 이 화면을 지금 현재 SQL 구문으로 지금 할 거기 때문에 계정 먼저 만들고 그 다음에기에 룰을 이용을 해서 프리빌리지를 받아야 된다는 거죠.",
          "<09:34:40> 권한 보게 여기가 어디냐면 지금 그냥 메인 하단계 제일 첫 번째 코드 올라오데 쇼그랜트스라고 하는 걸로 살짝...",
          "<09:54:35> 이런 식으로 접근하시면 되고요. 그다음에 데이터베이스 DB 수준 권한을 주고 싶어...",
          "<09:57:09> 나 생성 유저로 하겠어 그고 나서 유 유저에 로카호스트라는 걸로 하겠어 그 다음에 비밀번호는 뉴 패스워드로 하겠어 이런 식으로 하나 준다는 거지 이렇게 일단은 실행을 한번 해보면",
          "<10:05:01> 이렇게 해서 하나 구현하시면 돼요.",
          "<10:06:31> 그서 커맨드 열어서 ISQL의 마이나 U 뉴 유저 마이너 P로 일단 접속해보자 여기까지 하시고 천천히 현재 여기까지 하셨으면정 생성 권한 부여 권한 확인까지 하셨으면 나는 싫은데 여기 하나 더 킬 거야.",
          "<10:24:01> 잠깐만 있어봐요. 추가 확인했죠.",
          "<10:25:13> 들어오셔서 한번 넣고 천천히 하세요."
        ],
        "reasoning": "이론 설명 후 실습으로 자연스럽게 연결되며, 실습 내용이 이론과 관련되어 있습니다. 강사가 이전 수업 내용을 언급하며 실습을 진행하겠다고 명시적으로 언급하고 있습니다. | 이론 설명 후 SQL 구문을 사용하여 실습으로 자연스럽게 연결되며, 실습 내용이 이론과 관련되어 있습니다. | 이론 설명 후 실습으로 자연스럽게 연결되며, 실습 내용이 이론과 관련되어 있음. 실습 전환이 명확하게 이루어짐.",
        "confidence": 0.82,
        "caveats": [
          "이론 설명 후 실습으로의 자연스러운 연결이 전혀 없음.",
          "스크립트 내용이 불완전하여 실습 연계성을 평가하기 어려움."
        ]
      }
    ],
    "5. 수강생 상호작용": [
      {
        "item_id": "5.1",
        "item_name": "오류 대응",
        "category": "5. 수강생 상호작용",
        "score": 3,
        "weight": "MEDIUM",
        "evidence": [
          "<09:35:01> 얘는 지금 권한확인인데 그냥 권한 확인이 아니고 현재 로그인 권한 확인이에요.",
          "<09:57:09> 나 생성 유저로 하겠어 그고 나서 유 유저에 로카호스트라는 걸로 하겠어",
          "<10:01:29> 되셨어요습니다. 잠깐",
          "<10:08:04> 그래서 여기 유즈 마이 언더바 테스트를 했더니, 너 접근 권한이 없어 그래서 여기 에라 1044가 나와요.",
          "<10:23:30> 그런데 실제 거기서 IP를 지정을 하게 되면 프로모스트가 해당 IP를 찾아서 접속하는 상태에 수신을 하기 때문에 실제 그냥 하시면 안 되고",
          "<10:24:00> 그렇게 접속하셔야 돼 거기다가 호스트라고 이렇게 하나 주셔야 마이에스켈이 가지고 있는 뉴마이에 호스트를 주시고 접근하셔야 된다.",
          "<11:14:30> 확인 들갔나 확인 이제 실행 한번 해보고 그 다음에 다시 한번 확인하면 없어져 이거 있어도 실행이 되는 거라고 빨간 거 있어도 실행이 되는 거니까 걱정하지 말고 하세요.",
          "<12:03:50> 여러분들 다 어디 갔다 오셨어요.",
          "<12:04:00> 갑자기 막 우두두두 다 나가시던데 저만 나갔어요.",
          "<01:24:04> 저희가 일반적으로 데이터 타입을 사용하는 것이 아니라 해당 속성에 대한 어트리뷰트 속성 정보를 J슨 타입으로 줘서 이렇게"
        ],
        "reasoning": "강의 중 오류 발생에 대한 언급이 없으므로, 오류 대응 여부를 평가할 수 없음. | 스크립트에서 오류 발생에 대한 언급이 없으므로, 오류 대응 여부를 평가할 수 없음. | 강사가 오류 발생 시 적절히 대응하고 있지만, 설명이 다소 간략하여 추가적인 디버깅 과정이나 학습 기회로 전환하는 부분이 부족함.",
        "confidence": 0.8,
        "caveats": [
          "STT 오류로 인해 일부 발언이 누락되었을 가능성 있음",
          "수강생의 발언이 강사로 잘못 인식될 가능성 있음",
          "일부 오류 상황에 대한 설명이 간략할 수 있음",
          "STT 오류로 인해 강사의 발언이 정확히 전달되지 않았을 가능성 있음",
          "실습 중 오류가 발생하지 않았을 가능성 있음"
        ]
      },
      {
        "item_id": "5.2",
        "item_name": "이해 확인 질문",
        "category": "5. 수강생 상호작용",
        "score": 3,
        "weight": "HIGH",
        "evidence": [
          "<09:12:01> 어제 했던 내용을 3번 가도록 할게요",
          "<09:16:12> 혹시 기억나실까요?",
          "<09:30:29> 혹시나 여러분들께 보시면서 화면을 전환했더니 저블이 되죠.",
          "<09:37:31> 혹시 기억하실까요?",
          "<09:39:14> 여러분들 거 갖고 계시면 유저 프리빌리지의 저는 지금 마이디비의 프로모스트를 지금 퍼로 지금 바꾼 상태잖아요.",
          "<09:46:17> 이해 가능",
          "<09:47:23> 되셨어요.",
          "<10:01:29> 되셨어요습니다. 잠깐",
          "<10:04:51> 이해는 안 했나 보다 이렇게 이 테스트 여기서 두 가지 다 해보세요.",
          "<10:05:01> 이해는 안 했나 보다 이렇게 이 테스트 여기서 두 가지 다 해보세요."
        ],
        "reasoning": "이해 확인 질문이 있으나 빈도가 낮고 형식적임. 주요 개념 설명 후 이해 여부를 확인하는 질문이 부족함. | 이해 확인 질문이 있으나 빈도가 낮고 형식적임. 추가적인 질문이 필요함. | 주요 개념 설명 후 이해 확인 질문을 자주 하며, 수강생의 이해도를 점검하는 질문을 활용하고 있음.",
        "confidence": 0.81,
        "caveats": [
          "화자 구분 부정확으로 일부 확인 질문 누락 가능",
          "질문이 수강생의 이해도를 깊이 있게 점검하지 못할 가능성",
          "일부 질문이 수강생의 이해도를 깊이 있게 점검하지 못할 가능성",
          "스크립트가 짧아 이해 확인 질문 여부를 판단하기 어려움",
          "화자 구분 부정확으로 일부 질문 누락 가능"
        ]
      },
      {
        "item_id": "5.3",
        "item_name": "참여 유도",
        "category": "5. 수강생 상호작용",
        "score": 3,
        "weight": "HIGH",
        "evidence": [
          "<09:39:32> 그런데 만약에 사사님은 여기에 지금 내가 만든 계정에 여기 프로모스트가 로컬 호스트야가 뒤에가 그리고 내가 여기다가 불을 주고 글로벌 풀리빌리지를 지금 받은 상태야 이렇게 해서 생각한다면.",
          "<09:47:49> 이렇게 얘만 보지 말고 이렇게",
          "<09:48:11> 여기에 지금 유저 세션하고 여기 보면 시스 있었죠.",
          "<09:56:19> 확인을 좀 해봅시다",
          "<10:04:32> 여러분들 지금 여기까지 권한 설정을 했었는데 여기에서 지금 얘 하나 지금 이거 뉴언더바 테스트도 지금 하셨을 거 만들어놓은 거 여기도 확인하세요.",
          "<10:01:38> 쉬셨으면 저는 여기서 권한 부여를 여기다가 권한 확인을 한번 해봐요.",
          "<10:04:32> 여러분들 지금 여기까지 권한 설정을 했었는데 여기에서 지금 얘 하나 지금 이거 뉴언더바 테스트도 지금 하셨을 거 만들어놓은 거 여기도 확인하세요.",
          "<10:24:23> CMD 창 하나 아니면 다른 곳에서 접속 그러 이렇게 되는 거지",
          "<10:25:13> 들어오셔서 한번 넣고 천천히 하세요.",
          "<11:14:04> 한번 해보시면 여러분 지금 오른쪽은 약간쪽로 와야 돼요."
        ],
        "reasoning": "대부분 일방적 설명으로 수강생 참여 유도가 거의 없음. 참여를 유도하는 표현이 부족함. | 대부분 일방적 설명으로, 수강생 참여 유도가 거의 없음. | 수강생 참여를 유도하는 발언이 있으나, 빈도가 낮고 형식적인 질문이 많아 실질적인 참여 유도가 부족함.",
        "confidence": 0.78,
        "caveats": [
          "수강생 참여 유도 표현이 부족함",
          "일부 참여 유도 발언이 STT 오류로 인해 누락될 가능성 있음",
          "일부 참여 유도 표현이 다소 형식적일 수 있음",
          "STT 오류로 인해 수강생의 반응이 정확히 기록되지 않았을 가능성 있음",
          "참여 유도 표현이 명확하지 않을 수 있음"
        ]
      },
      {
        "item_id": "5.4",
        "item_name": "질문 응답 충분성",
        "category": "5. 수강생 상호작용",
        "score": 3,
        "weight": "HIGH",
        "evidence": [
          "<09:35:17> 내가 지금 현재 여기 루트로 로컬호스트가 지금 되어 있죠.",
          "<09:40:38> 이렇게 프록시온에 그랜트 옵션을 줄 수 있는 슈퍼유저 이건 없지만.",
          "<09:54:20> 그래서 이거 하려고 그러면 보통 크리에이트 권한 전체 권한이 크리에이트 유저 셧다운 파일 릴로드 프로세스 슈퍼 이렇게 해서 접근 권한을 줄 수가 있고",
          "<10:01:29> 되셨어요습니다. 잠깐",
          "<10:04:51> 이해는 안 했나 보다 이렇게 이 테스트 여기서 두 가지 다 해보세요.",
          "<10:08:11> 그고 나서 유즈에서 마이 언더바 EMP 했더니, 얘는 데이터베이스 체인지드가 되는 거예요.",
          "<10:24:00> 그렇게 접속하셔야 돼 거기다가 호스트라고 이렇게 하나 주셔야 마이에스켈이 가지고 있는 뉴마이에 호스트를 주시고 접근하셔야 된다.",
          "<11:04:39> 권한 추가를 기존에 맨 처음에 생성할 때는 뉴 마이라고 하는 것에 마이 EMP만 줬었는데 지금은 다시 그란트나 올 전체 다 줄 거야.",
          "<11:23:39> 자 그 다음에 딱 내려가서 권한이 없으니까 권한을 지정을 해 올 프리빌리지 온 투 나 마이 샘플에다가 다 줄 거야.",
          "<01:25:14> 이렇게 그렇죠. 사용자 정보를 그냥 저장하는 용도로 볼 수 있습니다."
        ],
        "reasoning": "수강생 질문에 대한 응답이 관찰되지 않아 질문 응답의 충분성을 평가할 수 없음. | 질문에 대한 응답이 부족하거나 주제에서 벗어난 경우가 있음. | 수강생 질문에 대해 명확하고 충분한 답변을 제공하며, 관련 배경 지식도 함께 설명하고 있음.",
        "confidence": 0.76,
        "caveats": [
          "STT 오류로 인해 질문 응답 내용이 불완전할 수 있음",
          "답변의 구체성이 부족하여 수강생의 이해를 돕지 못할 가능성",
          "질문에 대한 구체적인 응답이 부족할 수 있음",
          "수강생 질문이 관찰되지 않아 평가가 제한적임",
          "수강생 질문이 없었을 가능성 있음"
        ]
      }
    ]
  },
  "report_markdown": "# 강의 품질 분석 리포트\n\n## 1. 종합 요약\n- 가중 평균 점수: 2.93 / 5.0  \n- 가중 총점: 132.0  \n\n강의는 전반적으로 학습 목표와 전날 복습을 잘 연계하였으나, 언어 표현의 반복성과 발화 완결성, 설명 순서 및 핵심 내용 강조에서 개선이 필요합니다. 수강생의 이해를 돕기 위한 비유와 예시 활용이 부족하며, 마무리 요약이 전혀 이루어지지 않아 강의의 흐름이 매끄럽지 않았습니다.\n\n## 2. 카테고리별 상세 평가\n### 1. 언어 표현 품질 (점수: 3/5)\n- **불필요한 반복 표현** (점수: 3/5)  \n  - **근거**: '저희', '그 다음에'와 같은 표현이 반복됨.  \n  - **개선 제안**: 다양한 표현을 사용하여 반복을 줄이고, 강의의 흐름을 자연스럽게 유지할 필요가 있음.\n\n- **발화 완결성** (점수: 3/5)  \n  - **근거**: 비완결 문장이 간간이 나타나며, 의미 파악이 어려운 경우가 있음.  \n  - **개선 제안**: 문장을 명확히 완결짓고, 주어와 서술어를 분명히 하여 수강생이 이해하기 쉽게 해야 함.\n\n- **언어 일관성** (점수: 4/5)  \n  - **근거**: 대체로 존댓말로 일관되지만, 반말이 혼용됨.  \n  - **개선 제안**: 존댓말을 일관되게 사용하여 어색함을 줄여야 함.\n\n### 2. 강의 도입 및 구조 (점수: 3.2/5)\n- **학습 목표 안내** (점수: 4/5)  \n  - **근거**: 강의 시작 후 1분 이내에 학습 목표를 언급함.  \n  - **개선 제안**: 목표를 더욱 명확히 하고, 수업의 흐름을 간단히 정리하는 것이 좋음.\n\n- **전날 복습 연계** (점수: 4/5)  \n  - **근거**: 이전 강의 내용을 잘 연결함.  \n  - **개선 제안**: 복습 내용을 좀 더 구체적으로 언급하여 수강생의 기억을 돕는 것이 좋음.\n\n- **설명 순서** (점수: 2/5)  \n  - **근거**: 설명의 순서가 혼재되어 있음.  \n  - **개선 제안**: 개념 설명 후 예시를 제시하는 구조를 명확히 하고, 단계별로 설명하여 혼란을 줄여야 함.\n\n### 3. 개념 설명 명확성 (점수: 2.5/5)\n- **개념 정의** (점수: 2/5)  \n  - **근거**: 일부 개념이 정의 없이 사용됨.  \n  - **개선 제안**: 주요 개념에 대한 명확한 정의를 제공하여 수강생의 이해를 돕는 것이 필요함.\n\n- **비유 및 예시 활용** (점수: 2/5)  \n  - **근거**: 비유나 예시가 부족하여 설명이 추상적임.  \n  - **개선 제안**: 실생활 예시나 비유를 활용하여 개념을 쉽게 이해할 수 있도록 해야 함.\n\n### 4. 예시 및 실습 연계 (점수: 3.5/5)\n- **예시 적절성** (점수: 3/5)  \n  - **근거**: 예시가 제공되지만 구체성이 부족함.  \n  - **개선 제안**: 더 많은 실무 사례를 통해 수강생의 이해를 돕는 것이 필요함.\n\n- **실습 연계** (점수: 4/5)  \n  - **근거**: 이론 설명 후 실습으로 자연스럽게 연결됨.  \n  - **개선 제안**: 실습 전환을 더욱 명확히 하여 수강생이 실습 내용을 쉽게 따라올 수 있도록 해야 함.\n\n### 5. 수강생 상호작용 (점수: 3/5)\n- **오류 대응** (점수: 3/5)  \n  - **근거**: 오류 발생 시 적절한 대응이 부족함.  \n  - **개선 제안**: 오류 발생 시 추가적인 디버깅 과정이나 학습 기회로 전환하는 부분을 강화해야 함.\n\n- **이해 확인 질문** (점수: 3/5)  \n  - **근거**: 이해 확인 질문이 빈도가 낮고 형식적임.  \n  - **개선 제안**: 주요 개념 설명 후 자주 이해 여부를 확인하는 질문을 활용해야 함.\n\n## 3. 잘한 점 (강점)\n- 강의 시작 후 1분 이내에 학습 목표를 명확히 제시함.\n- 전날 복습 내용을 자연스럽게 연결하여 수업을 진행함.\n- 이론 설명 후 실습으로 자연스럽게 전환함.\n\n## 4. 개선 필요 사항\n- 반복적인 표현 사용으로 인해 강의 흐름이 매끄럽지 않음.\n- 비완결 문장이 간간이 나타나 수강생의 이해를 방해함.\n- 마무리 요약이 전혀 이루어지지 않아 강의가 갑자기 종료됨.\n\n## 5. 추천 개선 방향\n- 다양한 표현을 사용하여 반복을 줄이고, 문장을 명확히 완결짓기.\n- 주요 개념에 대한 명확한 정의와 실생활 예시를 활용하여 설명하기.\n- 강의 마무리 시 요약을 통해 핵심 내용을 정리하기.",
  "strengths": [
    "강의 시작 후 1분 이내에 학습 목표를 명확히 제시함.",
    "전날 복습 내용을 자연스럽게 연결하여 수업을 진행함.",
    "이론 설명 후 실습으로 자연스럽게 전환함."
  ],
  "improvements": [
    "반복적인 표현 사용으로 인해 강의 흐름이 매끄럽지 않음.",
    "비완결 문장이 간간이 나타나 수강생의 이해를 방해함.",
    "마무리 요약이 전혀 이루어지지 않아 강의가 갑자기 종료됨."
  ],
  "recommendations": [
    "다양한 표현을 사용하여 반복을 줄이고, 문장을 명확히 완결짓기.",
    "주요 개념에 대한 명확한 정의와 실생활 예시를 활용하여 설명하기.",
    "강의 마무리 시 요약을 통해 핵심 내용을 정리하기."
  ],
  "token_usage": {},
  "cost_usd": 0
}