{
  "lecture_date": "2026-02-13",
  "pass_num": 0,
  "transcript_path": "/Users/youngjinson/멋사-인턴/NLP 과제 1 - AI 강의 분석 리포트 생성기/강의 스크립트/2026-02-13_kdt-backendj-21th.txt",
  "metadata": {
    "course_id": "",
    "course_name": "백엔드 부트캠프 21기: Java",
    "date": "2026-02-13",
    "subjects": [
      "Front-End Programming"
    ],
    "contents": [
      "컴포넌트 스타일링(테일윈드 등)"
    ],
    "instructor": "김영아",
    "sub_instructors": [
      "김다은",
      "정석현"
    ]
  },
  "category_results": [
    {
      "category_name": "1. 언어 표현 품질",
      "items": [
        {
          "item_id": "1.1",
          "item_name": "불필요한 반복 표현",
          "category": "1. 언어 표현 품질",
          "score": 3,
          "weight": "HIGH",
          "evidence": [
            "<09:10:57> ... 이제 ...",
            "<09:12:11> ... 저희가 이제 ...",
            "<09:16:01> ... 얘를 하면서 얘를 구현하는 내용이라 ...",
            "<09:35:45> ... 지금 현재 이제 ...",
            "<09:39:11> ... 자식이 되는 거야.",
            "<09:39:18> ... 그러면 살짝 이거를 지금 현재 이 구조 ...",
            "<09:45:30> ... 이렇게 해서 정리 살짝 이렇게 세 가지고 있으면 ...",
            "<09:46:04> ... 그래서 지금 현재 어제 했던 그 마지막 ...",
            "<09:57:06> ... 그럼 생성 자체가 불가능해 FK가 불가능해 ...",
            "<10:01:24> ... 그래서 연결되어 있지 않고 연결이 되어 있어도 ..."
          ],
          "reasoning": "습관적 표현 '이제'와 '저희가 이제'가 해당 구간에서 분당 약 4회 관찰됨. 반복이 있지만 내용 전달에 큰 문제는 없음. | 습관적 표현 '지금 현재', '이제', '살짝' 등이 반복적으로 사용되어 강의 흐름을 방해함. | 반복 표현 '독립'과 '비식별 관계'가 빈번하게 나타나 강의 흐름을 방해함. 특히 '독립'이라는 표현이 여러 번 반복됨.",
          "confidence": 0.76,
          "caveats": [
            "STT 오인식으로 인한 반복 가능성 일부 존재"
          ]
        },
        {
          "item_id": "1.2",
          "item_name": "발화 완결성",
          "category": "1. 언어 표현 품질",
          "score": 3,
          "weight": "MEDIUM",
          "evidence": [
            "<09:11:35> ... 시스 스키마라는 것을 가지고 ...",
            "<09:12:23> ... 이렇게 해서 세 가지 카테고리를 가지고 ...",
            "<09:37:21> ... 그래서 ...",
            "<09:39:39> ... 작성을 하다 보면 내가 나도 모르게 자식이 되고 ...",
            "<09:40:04> ... 약간 이런 먼저 만들어져서 약간 이런 느낌도 맞아 ...",
            "<09:57:58> ... 자식 테이블에 참조하고 있으므로 삭제 거부된다.",
            "<10:01:21> ... 그래서 얘가 이렇게 표시가 된다고 했어요.",
            "<10:02:12> ... 끊어버리는 거지 따다 부모 자식 관계는 있지만 내가 PK값 안 받아도 돼 나 돈이 있어.",
            "<10:10:41> ... 얘기가 캐스케이드 옵션이 있기 때문이고 노액션 옵션이 있기 때문에 온 딜리트 온 업데이트 식별관계는 한다.",
            "<10:25:43> ... 연결되어었을 때 CRD를 하게 되면 어떤 역량을 가질 수 있는지를 우리가 한눈에 볼 수 있 ..."
          ],
          "reasoning": "대체로 문장이 완결되며, 간혹 비완결 문장이 나타나지만 이해에 문제 없음. | 비완결 문장이 간헐적으로 나타나며, 때로 의미 파악이 어려운 경우가 있음. | 비완결 문장이 간간이 나타나며, 특히 문장 중간에 주제가 전환되는 경우가 있어 수강생이 의미를 추론해야 하는 경우가 발생.",
          "confidence": 0.71,
          "caveats": [
            "STT 오류로 인한 문장 끊김은 감점 대상에서 제외"
          ]
        },
        {
          "item_id": "1.3",
          "item_name": "언어 일관성",
          "category": "1. 언어 표현 품질",
          "score": 4,
          "weight": "MEDIUM",
          "evidence": [
            "<09:10:38> ... 안녕하세요.",
            "<09:10:41> ... 저희 수업 진행하도록 하겠습니다.",
            "<09:35:38> ... 됐습니까?",
            "<09:39:11> ... 자식이 되는 거야.",
            "<09:39:18> ... 그러면 살짝 이거를 ...",
            "<09:45:30> ... 이렇게 해서 정리 살짝 ...",
            "<09:57:06> ... 그럼 생성 자체가 불가능해 FK가 불가능해 ...",
            "<10:00:44> ... 제가 이렇게 해서 말씀드렸는데.",
            "<10:01:00> ... 내가 뭐라고 그랬어요. 그렇지.",
            "<10:11:10> ... 그러면 다시 원래대로 가도록 하겠습니다."
          ],
          "reasoning": "대체로 존댓말로 일관되지만, 특정 구간에서 반말이 혼용되어 어색함이 관찰됨. | 대체로 일관되지만 특정 구간에서 존댓말과 반말이 혼용되어 어색함. | 대체로 존댓말이 사용되지만, 특정 구간에서 반말이 혼용되어 어색함이 느껴짐. 그러나 전반적으로는 일관성이 유지됨.",
          "confidence": 0.78,
          "caveats": [
            "수강생과 대화 시 톤 변화는 자연스러운 것으로 봄"
          ]
        }
      ],
      "weighted_average": 3.2857142857142856
    },
    {
      "category_name": "2. 강의 도입 및 구조",
      "items": [
        {
          "item_id": "2.1",
          "item_name": "학습 목표 안내",
          "category": "2. 강의 도입 및 구조",
          "score": 4,
          "weight": "HIGH",
          "evidence": [
            "<09:10:57> 저희 이제 오늘은 13일 수업이고 그 다음에 오늘 수업 끝나면 이제 연휴라서 오늘 좀 행복하게 수업 진행해 보도록 할 저희 어제는 그 마이에스큐L이 가지고 있는 크레트 구먼을 어제 진행을 하셨습니다데..."
          ],
          "reasoning": "강의 시작 후 2분 내에 학습 목표를 언급하고, 어제의 내용을 간략히 설명하며 오늘의 수업 흐름을 안내함.",
          "confidence": 0.85,
          "caveats": []
        },
        {
          "item_id": "2.2",
          "item_name": "전날 복습 연계",
          "category": "2. 강의 도입 및 구조",
          "score": 5,
          "weight": "HIGH",
          "evidence": [
            "<09:10:57> 저희 어제는 그 마이에스큐L이 가지고 있는 크레트 구먼을 어제 진행을 하셨습니다데..."
          ],
          "reasoning": "어제의 수업 내용을 명확히 복습하고, 오늘의 수업과의 연결고리를 자연스럽게 설명함.",
          "confidence": 0.9,
          "caveats": []
        },
        {
          "item_id": "2.3",
          "item_name": "설명 순서",
          "category": "2. 강의 도입 및 구조",
          "score": 2,
          "weight": "MEDIUM",
          "evidence": [
            "<09:14:10> 이제 저희가 백엔드 프로그램을 하고 있기 때문에 이 트랜잭션을 어떻게 관리하는지를 알아야 저희가 이제 세션이 물려 있을 때 클라이언트가 서버에 접속했을 때 락을 건 상태에서 데이터 CRD의 보존성을 트랜잭션으로 저희가 관리를 할 수가 있습니다.",
            "<09:39:18> 그러면 살짝 이거를 지금 현재 이 구조 여기 지금 스턴트 마이에서 지금 제가 작성을 조금 해드리도록 하겠습니다.",
            "<10:10:30> 비식별 관계를 생각했을 때 데이터 무결성을 반드시 알아야 된다.",
            "<10:35:11> 오늘은 아침에 그렇게 어렵지 않죠 여기 이제 오늘 저희가 이제 그 아침부터 비식별 관계를 설명하고 참조를 지금 설명하고 있는데,",
            "<11:15:02> DDL은 버퍼를 사용하지 않고 알터 이런 명령들이지 이게 DDL 데이터 정의어인데 얘는 실행 즉시 커밋이 실제 데이터 디스크 상태로 저장하는 애야...",
            "<11:19:28> 그래서 롤백이 인서트 딜리트 업데이트 한 거를 되돌린까지는 일단 우리가 확인했어요.",
            "<11:40:38> 이해 가요 이런 식으로 가는 게 트랜잭션의 원리인 거야.",
            "<01:17:50> 트랜잭션의 특징은 이건 시험 문제 필수 트랜잭션은 원래 ACID 원칙이라는 게 맨 처음에 나오자마자...",
            "<01:22:15> 일단은 이런 역할들이 있고 이런 명령어까지 있어요.",
            "<01:23:11> 그러면 여기 앞에랑기 커밋이야 그래서 지금 이거 URL 3개 섹션을 지금 스레드에다가 공유를 해드렸잖아요."
          ],
          "reasoning": "대체로 구조적이며 개념, 예시, 실습의 흐름이 자연스러움. 그러나 일부 단계 간 전환이 명시적이지 않음. | 개념, 예시, 실습의 순서가 혼재되어 있으며, 설명의 흐름이 일관되지 않음. | 구조가 있지만 때때로 순서가 뒤바뀌거나 단계가 생략됨.",
          "confidence": 0.73,
          "caveats": []
        },
        {
          "item_id": "2.4",
          "item_name": "핵심 내용 강조",
          "category": "2. 강의 도입 및 구조",
          "score": 2,
          "weight": "MEDIUM",
          "evidence": [
            "<09:15:53> 오늘은 핵심이 인서트 딜리트 업데이트가 얘니다.",
            "<09:46:32> 부모 테이블의 3대 필수 요건으로 대신할 수 있어 지금 제가 말은 이렇게 적어놨는데 이게 지금",
            "<10:10:30> 비식별 관계를 생각했을 때 데이터 무결성을 반드시 알아야 된다.",
            "<10:34:44> 외래키 맵핑 정보라고 제가 써놨어요.",
            "<11:15:34> 그래서 얘는 트랜젝션 취소 대상에 포함되지 않아 빼이 불가능해 하여 벌써 저장해버렸어 롤백 불가능...",
            "<11:40:50> 이해 가요 이런 식으로 가는 게 트랜잭션의 원리인 거야.",
            "<11:40:38> 이해 가요 이런 식으로 가는 게 트랜잭션의 원리인 거야.",
            "<01:17:50> 트랜잭션은 원래 ACID 원칙이라는 게 맨 처음에 나오자마자...",
            "<01:31:01> 내가 내 맘대로 커밋하고 내가 내 맘대로 인서트 한 사람이 커밋하고 인서트 한 사람이 롤백 해야 되는 거 아니냐.",
            "<01:56:39> 아시겠죠."
          ],
          "reasoning": "핵심 내용을 자연스럽게 반복하여 설명하고 강조함. 그러나 일부 중요한 내용은 강조가 부족할 수 있음. | 일부 중요한 내용을 강조하지만, 체계적이지 않음. | 핵심 내용을 자연스럽게 반복하여 설명하고 강조함.",
          "confidence": 0.73,
          "caveats": []
        },
        {
          "item_id": "2.5",
          "item_name": "마무리 요약",
          "category": "2. 강의 도입 및 구조",
          "score": 1,
          "weight": "LOW",
          "evidence": [
            "<05:50:05> 여러분 한 주간 고생 많으셨습니다.",
            "<05:50:21> 시간 명절 잘 보내시고 잘 쉬시고 기분 좋게 6월 23일 날 뵙도록 할게요 수고하셨습니다."
          ],
          "reasoning": "강의 마무리 요약이 전혀 없으며, 강의가 종료되는 형식으로만 진행되고 있습니다.",
          "confidence": 0.9,
          "caveats": []
        }
      ],
      "weighted_average": 3.272727272727273
    },
    {
      "category_name": "3. 개념 설명 명확성",
      "items": [
        {
          "item_id": "3.1",
          "item_name": "개념 정의",
          "category": "3. 개념 설명 명확성",
          "score": 3,
          "weight": "HIGH",
          "evidence": [
            "<09:14:10> 이제 저희가 백엔드 프로그램을 하고 있기 때문에 이 트랜잭션을 어떻게 관리하는지를 알아야 저희가 이제 세션이 물려 있을 때 클라이언트가 서버에 접속했을 때 락을 건 상태에서 데이터 CRD의 보존성을 트랜잭션으로 저희가 관리를 할 수가 있습니다.",
            "<09:39:18> 그러면 살짝 이거를 지금 현재 이 구조 여기 지금 스턴트 마이에서 지금 제가 작성을 조금 해드리도록 하겠습니다.",
            "<10:01:39> 그래서 연결되어 있지 않고 연결이 되어 있어도 그냥 직선으로 연결되 있는 게 아니라 나는 나 따로 독립했으니까 지원 안 받아도 돼 그래서 얘가 이렇게 표시가 된다고 했어요.",
            "<10:35:11> 비식별 관계를 설명하고 참조를 지금 설명하고 있는데, 여기에서 얘 같은 경우에는 전용 참조 테이블의 정보를 가지고 이거는 크 컨스트레인티스를 가지고 이거 했더니, 뭐가 나왔어요.",
            "<11:04:27> 자 그 다음에 언더바 EMP 테이블에 자 여기 제약 조건을 하나 칼럼을 추가를 해보자 이렇게 해서 하나 이렇게 살짝 까시고 CMP로 확인을 한번",
            "<11:17:26> 롤백 커밋 중에 두 개를 하겠다는 건데 이렇게가 롤백이야 이렇게 해서 하나 살짝 정리 여기서는 정시적인 트랜잭션 종료를 하는 명령어 하트 트랜잭션이라는 애를 정료하는 롤백이고 마지막 코밋 스타트 트랜잭션 선언했던 트랜잭션의 시작점으로 돌아갑니다.",
            "<11:40:50> 여러 개의 세션이 동일한 데이터를 접속했을 때 최초 접속했던 내용이 스토리지에서 가지고 온 거고, 인서트 딜리트 업데이트가...",
            "<01:13:42> 저희가 이제 개념은 아침에 오전 수업에서 살짝 눈도는 스타트 트랜잭션이라고 하는 것은 트랜잭션 시작을 알리는 거고, 명시적으로 커밋은...",
            "<01:21:39> 이런 거랑 똑같아요어서 나중에 우리가 자바로 데이터베이스에 데이터를 가지고 왔어 게시판을 오픈을 오픈했는데 실제적으로 동시에 뭐 10명이 똑같은 게시글 하나를 가지고는 수정하려고 그러고 하나는 삭제하려고 그러고 이런 것들은 어떻게 처리하는 거예요.",
            "<01:49:19> 0으로 줘야 롤백을 할 수가 있고 자 셋에 가서 오토커밋을 0을 주면 지금 SQL 서버를 서버에서 완전히 변경된다."
          ],
          "reasoning": "트랜잭션 개념이 등장했으나 명확한 정의 없이 사용되고 있어 수강생이 이해하기 어려울 수 있음. | 일부 개념은 정의 없이 사용되지만, 전체적으로 이해에 큰 문제는 없음. 예를 들어, '부모 테이블'과 '자식 테이블'의 개념은 설명되지만 명확한 정의는 부족함. | 강의 중 여러 개념이 언급되지만, 명확한 정의가 부족하여 수강생이 이해하기 어려울 수 있음. 특히 '비식별 관계'와 '식별 관계'에 대한 명확한 설명이 부족함.",
          "confidence": 0.71,
          "caveats": [
            "STT 특성상 기술 용어 인식 오류 가능"
          ]
        },
        {
          "item_id": "3.2",
          "item_name": "비유 및 예시 활용",
          "category": "3. 개념 설명 명확성",
          "score": 3,
          "weight": "HIGH",
          "evidence": [
            "<09:25:03> 말 그대로 릴레이션십이라서 RD를 할 수 있는 테이블 한 개가 아니고 연결되어 있는서 살짝 이런 것들을 물어봐요.",
            "<09:43:40> 예를 들면 회사가 있어야 사원이 있는 거죠서 뎁트 테이블이 먼저 부모가 되는 거고, 그다음에 사원이 EMP 테이블이거든요.",
            "<10:11:00> 독립한 애들의 특징을 가만히 생각해보면 사람 사는 거랑 지금 똑같아 스케프 하겠습니다.",
            "<10:33:38> 여러분들 뭐 조별로 하실 때도 많이 쓰고 이렇게 하는데 좀 익숙해지면 이 워크벤치가 CMD보다 약간 불편할 수 있어요.",
            "<11:12:32> 우리가 익스플레인하고 우리 조인하고 이런 거 하면 거기에 뭐 MT도 나오고 그 다음에 템플러이 테이블도 나오고 막 이런 식으로 해서 돈 계산을 실행 예측이잖아요.",
            "<11:19:10> 그리고 여기서 트랜잭션을 명시적으로 종료하는 명령은 뭐야? 이러면 롤백이야 자 되셨어요. 옳지",
            "<11:40:38> 이해 가요 이런 식으로 가는 게 트랜잭션의 원리인 거야.",
            "<01:20:01> 예를 들어서 어떤 작은 부에 돈이 만 원이 있어 이거를 작은 부 은행은 자금부라는 게 있거든.",
            "<01:31:01> 내가 내 맘대로 롤백하고 내가 내 맘대로 코밋할 수 있게끔 만들어 놨단 말이야.",
            "<01:57:07> 결론은 스타트 트랜잭션은 커밋과 롤백 두 개 중에 하나 만나면 종료가 되는 거고."
          ],
          "reasoning": "비유나 예시가 거의 없어 추상적 설명에 의존하고 있어 이해를 돕지 못함. | 어려운 개념에 대해 실생활 예시를 적절히 활용하고 있으며, 이해에 도움이 됨. 그러나 비유의 빈도가 다소 낮음. | 비유가 사용되긴 했으나, 비유의 빈도가 낮고 구체적인 실생활 예시가 부족하여 이해를 돕는 데 한계가 있음.",
          "confidence": 0.71,
          "caveats": [
            "STT 특성상 비유 표현이 누락되었을 가능성",
            "STT 특성상 비유의 정확한 표현이 어려울 수 있음",
            "STT 특성상 비유 표현이 부정확할 수 있음",
            "STT 특성상 비유 및 예시 인식 오류 가능",
            "STT 특성상 기술 용어 인식 오류 가능"
          ]
        },
        {
          "item_id": "3.3",
          "item_name": "선행 개념 확인",
          "category": "3. 개념 설명 명확성",
          "score": 3,
          "weight": "MEDIUM",
          "evidence": [
            "<09:12:23> 그중에서 테이블에 관련된 거 컬럼에 관련된 계약 조건에 관련된 거 이렇게 해서 세 가지 카테고리를 가지고 테이블을 봤었는데 일반 테이블 같은 경우에는 데이터베이스 생성하고 난 다음에 테이블의 구조를 가지고 있는 속성 값을 가지고 있었고,",
            "<09:39:11> 자식은 부모 눈치 살짝 보면서 참조해서 테이블을 생성해야 되는 이런 상황인 거지 되셨어요.",
            "<10:03:06> 식별은 데이터가 없어도 자식 데이터로 살 수 있는 그렇지 얘기했잖아.",
            "<10:35:25> 어미가 나왔죠 범위 어떻게 체크를 줬는지 끝까지 살짝 정리 여기는 뭐 다시 안 봐도 될 것 같습니다.",
            "<11:10:11> 이렇게 그래서 여기다가 마지막 커밋 명령 또는 스타트 트랜잭션 이렇게로 살짝 돌아가 이렇게 이 시점으로",
            "<11:19:03> 하고 내용을 보고 다시 롤백을 원래대로 돌아가더라 그런데 어디로 돌아가야 돼 마지막 커밋 상태 또는 스타트 트랜잭션이 선언했던 트랜잭션의 시작점으로 되돌아간다.",
            "<11:41:04> 우리가 보통 이렇게 쿼리 조작 언어인데 쿼리 조작 언어를 할 때는 기본적으로 내가 커밋을 할 건지 롤백을 할 건지를 일단은 결정을 해서 작업을 진행하게 된다죠.",
            "<01:18:06> 그러면 데이터에 테이블 생성을 할 때 제약 조건을 생각하시면 그렇게 어렵지 않아요.",
            "<01:22:07> 이런 건 다 서버가 처리하는 거예요.",
            "<01:55:52> 지금 DML 연습해보자 이렇게 했으니까 자 이제 스타트 트랜잭션 하겠다."
          ],
          "reasoning": "선행 개념을 고려하여 설명하고 있으나, 일부 심화 내용으로의 점프가 존재함. | 대체로 선행 개념을 고려하며 설명하고 있으나, 가끔 심화 내용으로 넘어가는 경향이 있음. | 선행 개념에 대한 언급이 있지만, 때때로 심화 내용으로 넘어가는 경향이 있어 수강생이 따라가기 어려울 수 있음.",
          "confidence": 0.69,
          "caveats": [
            "STT 특성상 문맥이 불명확할 수 있음",
            "STT 특성상 문장 경계 인식 오류 가능",
            "STT 특성상 기술 용어 인식 오류 가능",
            "STT 특성상 문장 경계가 불명확할 수 있음"
          ]
        },
        {
          "item_id": "3.4",
          "item_name": "발화 속도 적절성",
          "category": "3. 개념 설명 명확성",
          "score": 4,
          "weight": "MEDIUM",
          "evidence": [
            "<09:14:45> 그래서 커믹과 롤백이라는 것을 잘 이용을 해서 무결성을 또 다른 서버나 아니면 클라이언트에게 어떻게 보여지는지 오늘 좀 확인할 거고,",
            "<09:46:32> 횟수 조건이 3번 기준인데 부모 테이블의 3대 필수 요건으로 대신할 수 있어 지금 제가 말은 이렇게 적어놨는데 이게 지금",
            "<10:10:30> 맞아 그래서 이 말이 뭐냐 말이 이렇게 비식별 관계에서는 자식 테이블의 데이터를 삭제하거나 수정할 때 부모 테이블의 식별 체계에다가 혼란을 주지 않는다.",
            "<10:34:09> 저도 여기서 코딩할 때랑 여기 CMD에서 코딩할 때랑 속도가 조금 다르거든요.",
            "<11:12:34> 실행 예측식 그래서 실행 예측 시간이라고 강사가 매번 얘기하고 그 다음에 실행 비용을 체크하겠다.",
            "<11:40:00> 이해 가요 이런 식으로 가는 게 트랜잭션의 원리인 거야.",
            "<11:42:54> 좀 답다해 정신 없다어 우기꺼 이제 알고는 있지만...",
            "<01:21:14> 해줘야 되는 거예서 동시에 여러 트랜잭션이 접근을 하게 되면 충돌이 발생할 수 있기 때문에 서버는 락이나 격리 수준 관리를 진행하게 된다.",
            "<01:30:20> 오토커밋 변수가 나와서 지금 시스템 배리어블리 기본값이 지금 오늘 어떻게 되어있는지 조금 이따 찾아보면 되는 거니까.",
            "<02:00:34> 실제 데이터가 생존해 있다는 거지 생존했어."
          ],
          "reasoning": "발화 속도가 일정하나 때때로 빠르거나 느려 조절이 부족하여 집중에 방해가 될 수 있음. | 속도가 일정하나 때때로 빠르거나 느려 조절이 부족하여 집중에 방해가 될 수 있음. | 전반적으로 발화 속도가 적절하나, 일부 구간에서 빠르게 진행되어 집중에 방해가 될 수 있음.",
          "confidence": 0.72,
          "caveats": [
            "STT 특성상 발화 속도 인식 오류 가능",
            "타임스탬프 간격으로 발화 밀도 추정",
            "타임스탬프 간격으로 발화 밀도 추정 필요",
            "STT 특성상 기술 용어 인식 오류 가능",
            "STT 특성상 발화 속도에 대한 인식 오류 가능"
          ]
        }
      ],
      "weighted_average": 3.2
    },
    {
      "category_name": "4. 예시 및 실습 연계",
      "items": [
        {
          "item_id": "4.1",
          "item_name": "예시 적절성",
          "category": "4. 예시 및 실습 연계",
          "score": 3,
          "weight": "HIGH",
          "evidence": [
            "<09:24:00> 이러면 테이블이 두 개가 릴레이션십이 되어 있는데, 기타 등등 얘기하면 프로시저하고 펑션의 사용성 이런 것들 물어보고 인제 아주 편안한 대화 이런 것들을 물어봅니다.",
            "<09:43:40> 예를 들면 회사가 있어야 사원이 있는 거죠서 뎁트 테이블이 먼저 부모가 되는 거고, 그다음에 사원이 EMP 테이블이거든요.",
            "<10:15:10> 예를 들면 상품 테이블 주문 테이블 하나 만들어 가지고...",
            "<10:30:05> 예를 들자면 뭐 이거나 얘나 FK 있는 애들 살짝 보세런 애들은...",
            "<11:02:14> 자 이렇게 해서 잠깐 이렇게 해서 드려야 되는데 이거 제가 어디서 하냐면 저는 VS코드도 연결해가지고 시퀀 쓰고 하니까 정렬하면 한 줄로 이렇게",
            "<11:19:10> 그리고 여기서 트랜잭션을 명시적으로 종료하는 명령은 뭐야? 이러면 롤백이야 자 되셨어요. 옳지",
            "<11:42:02> 그래서 이게 계약 조건이 추가 삭제 수정이 힘들어서 추가 수정 삭제하는 방법을 여기다가 살짝 적어놓고 유니크는 여기서 드랍 인덱스라는 걸로 하더라 까지 확인 내용으로 살짝 정리를 한번 하시면 어떨까",
            "<01:20:01> 예를 들어서 어떤 작은 부에 돈이 만 원이 있어 이거를 작은 부 은행은 자금부라는 게 있거든.",
            "<01:21:39> 이런 거랑 똑같아요어서 나중에 우리가 자바로 데이터베이스에 데이터를 가지고 왔어 게시판을 오픈을 오픈했는데 실제적으로 동시에 뭐 10명이 똑같은 게시글 하나를 가지고는 수정하려고 그러고 하나는 삭제하려고 그러고 이런 것들은 어떻게 처리하는 거예요.",
            "<01:55:52> 지금 DML 연습해보자 이렇게 했으니까 자 이제 스타트 트랜잭션 하겠다."
          ],
          "reasoning": "강의 중에 실제 데이터베이스의 테이블 간 관계를 설명하며, 프로시저와 펑션의 사용성을 예로 들어 실무에서의 적용 가능성을 언급하고 있어 수강생들이 이해하기 쉽게 연결되고 있습니다. | 강의에서 부모-자식 관계를 설명할 때, 실제 회사와 사원 간의 관계를 예로 들어 설명하여 수강생들이 이해하기 쉽게 연결하였습니다. | 강사가 실제 데이터베이스 설계와 관련된 예시를 통해 이론을 설명하고 있어, 수강생들이 실무에서 접할 수 있는 상황과 연관성이 높음.",
          "confidence": 0.77,
          "caveats": []
        },
        {
          "item_id": "4.2",
          "item_name": "실습 연계",
          "category": "4. 예시 및 실습 연계",
          "score": 4,
          "weight": "HIGH",
          "evidence": [
            "<09:27:12> 오늘 CRD라고 하는 파일 하나 드렸죠 네 이거 하나 살펴보면 어제 했던 내용들을 살짝 정리를 조금 트랜잭션이랑 해놓은 게 있으니까 이거 조금 보도록 할게요.",
            "<09:52:14> 이렇게 해서 온 딜리트 부모가 지금 현재 부모가요 삭제 뭐 수정되면식도 함께 삭제 수정되겠다.",
            "<10:12:02> 포린키 제약 조건 시 선택 옵션이라는 것이 있어요.",
            "<10:35:11> 오늘은 아침에 그렇게 어렵지 않죠 여기 이제 오늘 저희가 이제 그 아침부터 비식별 관계를 설명하고 참조를 지금 설명하고 있는데...",
            "<11:01:33> 자 이제 저희 그 풀이 잠깐 보고 오늘 수업 진행하도록 진도 나가도록 할게요 일단은 유즈 마이 EMP로 갑니다.",
            "<11:19:28> 그래서 롤백이 인서트 딜리트 업데이트 한 거를 되돌린까지는 일단 우리가 확인했어요.",
            "<11:36:20> 이런 거지 그다음에 이런 거 있으면 항상 얘도 넣어보고 싶어 물론 알고는 있지만 얘도 넣어보고 싶어 이렇게 그러면은 이제 키값이 하나 살짝 들어가 있으니까",
            "<11:44:14> 네 이렇게 해서 하시고 오후에는 제가 이 내용이랑 트랜잭션이랑 이런 것들을 조금 하면서 트윗 이런 것들 이게 지금 이걸로 뭐 관리하고 이런 거 있거든요.",
            "<01:25:01> 이해 가죠 스케이프 하고요. 그 다음에 여기다가 이제 트랜잭션이라고 하나 입력을 해볼다.",
            "<01:29:04> DML 작업에 대한 내용 그래서 사부작 하면 글 하나 만들어서 하트 트랜잭션하고 콘서트 한 다음에 서밋을 하는 거지 그리고 나서 여기에 셋 오토 커밋을스로 주고"
          ],
          "reasoning": "이론 설명 후 실습으로 자연스럽게 연결되며, 실습 내용이 이론과 관련되어 있어 수강생들이 직접 실습을 통해 이론을 강화할 수 있도록 잘 안내하고 있습니다. | 이론 설명 후 실습으로 자연스럽게 연결되었으나, 실습에 대한 명확한 전환 표현이 부족하여 연결이 다소 느슨하게 느껴졌습니다. | 이론 설명 후 실습으로 자연스럽게 연결되며, 실습 내용이 이론과 밀접하게 관련되어 있음. 강사가 실습을 통해 이론을 강화하는 방식으로 진행.",
          "confidence": 0.79,
          "caveats": []
        }
      ],
      "weighted_average": 3.5
    },
    {
      "category_name": "5. 수강생 상호작용",
      "items": [
        {
          "item_id": "5.1",
          "item_name": "오류 대응",
          "category": "5. 수강생 상호작용",
          "score": 2,
          "weight": "MEDIUM",
          "evidence": [
            "<09:29:33> 죄송합니다. 어제 이거 삭제 안하고 걸어놓고 갔나 봐",
            "<09:30:02> 그래서 지금 드랍이 안 되는 상태",
            "<09:51:06> 410d984d: 1215부터 시작해서 1255 몇 개 되지 않다 천 단위 몇 개 아니라서 1225 오류가 발생한다.",
            "<10:07:03> 여기까지 확인하셨을까요?",
            "<10:10:30> 맞아 그래서 이 말이 뭐냐 말이 이렇게 비식별 관계에서는 자식 테이블의 데이터를 삭제하거나 수정할 때 부모 테이블의 식별 체계에다가 혼란을 주지 않는다.",
            "<11:05:22> 아직까지 공부는 안 했지만, 업데이트 샘문이야 아 수정하겠어 그래 퀘스트 언더바 이제 EMP에 4를 전부 다 천으로 세팅하겠죠.",
            "<11:18:09> 그런데 강사님 나 지금 원래대로 돌아가지 않아 이렇게 얘가 지금 현재 오토코밋을 자동 저장 자동 저장을 뭐 1로 놨겠지 그건 이따 가서 한번 보자고요.",
            "<11:41:23> 내가 커밋을 할 건지 롤백을 할 건지를 일단은 결정을 해서 작업을 진행하게 된다죠 지금은 뭐 이게 지금 데이터가 커밋하든 롤백하든 지금 이렇게 여러분들이 이제 눈으로 확인하시면 되고요.",
            "<01:20:01> 이거를 트랜잭션으로 가져오기 시작하면 한쪽은 롤백 하려고 한쪽은 커밋하려고 하고 어떤 작업이랑 동일한 형태가 만들어져서 동시성 제어라고 하는 것은 하나의 데이터를 전혀 다른 곳에서 접속을 해서 전혀 다른 일을 하려고 하는 거야.",
            "<01:25:33> 여기다가 이제 트랜잭션이라고 하나 입력을 해볼다 지금 알아서 찾는구나 이게 A랑 왜 이렇게 안 눌러지는 거예요."
          ],
          "reasoning": "강사가 오류 발생 시 즉각적으로 상황을 인지하고 사과하며, 문제의 원인을 설명하고 있습니다. 다만, 해결 방법에 대한 구체적인 설명이 부족하여 4점으로 평가했습니다. | 강사가 오류에 대해 언급했지만, 구체적인 해결 방법이나 디버깅 과정에 대한 설명이 부족함. | 오류 발생 시 강사가 적절히 대응하고 있지만, 설명이 다소 간략하여 수강생이 혼란스러울 수 있는 부분이 있음.",
          "confidence": 0.77,
          "caveats": [
            "오류 발생에 대한 구체적인 대응이 부족하여 수강생의 혼란을 초래할 수 있음.",
            "수강생의 질문이 명확하지 않아 강사의 대응이 제한적일 수 있음",
            "오류 발생 여부가 명확하지 않음",
            "구체적인 오류 상황이 명시되지 않아 평가에 한계가 있음",
            "강의 내용이 짧아 오류 발생 여부를 판단하기 어려움"
          ]
        },
        {
          "item_id": "5.2",
          "item_name": "이해 확인 질문",
          "category": "5. 수강생 상호작용",
          "score": 3,
          "weight": "HIGH",
          "evidence": [
            "<09:39:11> 이해 가셨죠 여기서 참조하는 방향에 있는 테이블명이 모두 부모 테이블",
            "<09:39:18> 되셨어요. 네 좋아요.",
            "<09:39:11> 410d984d: 되셨어요. 네 좋아요.",
            "<09:45:30> 410d984d: 됐을까요?",
            "<10:07:03> 여기까지 확인하셨을까요?",
            "<10:08:20> 여기까지 되셨어요.",
            "<10:27:28> 되셨어요?",
            "<10:34:21> 됐어요.",
            "<11:19:10> 강사 여기 이제 0보다 1배만 받겠다고 해서 업데이트를 CRD 하니까 한번 써본 거 그래서 나는 업데이트 샘 업데이트는 테이블을 가져다가 전체 조건 없이 손으로 변경을 하겠다.",
            "<11:19:21> 이러면 롤백이야 자 되셨어요. 옳지"
          ],
          "reasoning": "이해 확인 질문이 있으나 빈도가 낮고, 질문이 형식적이며 수강생의 이해도를 깊이 있게 점검하지 못하고 있습니다. | 주요 개념 설명 후 이해 확인 질문을 주기적으로 활용하고 있으며, 수강생의 이해도를 점검하는 질문을 하고 있음. | 주요 개념 설명 후 이해 확인 질문을 자주 하며, 수강생의 이해도를 점검하는 질문을 활용하고 있음.",
          "confidence": 0.81,
          "caveats": [
            "일부 질문이 수강생의 이해도를 깊이 있게 점검하지 못할 수 있음",
            "이해 확인 질문이 있지만, 수강생의 반응을 확인할 수 있는 구간이 부족함",
            "화자 구분 부정확으로 일부 확인 질문 누락 가능",
            "일부 확인 질문이 누락될 수 있음.",
            "일부 질문이 형식적일 수 있으며, 수강생의 반응이 명확하지 않음."
          ]
        },
        {
          "item_id": "5.3",
          "item_name": "참여 유도",
          "category": "5. 수강생 상호작용",
          "score": 3,
          "weight": "HIGH",
          "evidence": [
            "<09:28:06> 8로 살짝 오셔서 드랍 좀 하고요.",
            "<09:31:32> 그러면 여기가 지금 스튜던트스 얘거든요.",
            "<09:39:32> 410d984d: 그래서 여기다가 살짝 왜냐하면, 지금 저쪽 워크벤치에다가 제가 위에다가 그릴 수가 없어서 여기다가 살짝 적어드릴게요.",
            "<10:12:02> 프리 들어가서 한번 샤부작 같이 돌려보도록 하겠습니다.",
            "<10:10:47> 정리하는 그런 또 시간이 있겠죠.",
            "<10:26:09> 혼자 풀이한다고 그랬죠 풀이 한번 열어보도록 하겠습니다.",
            "<10:28:30> 애들은 좀 많지만으니까 옳지 이제 밑에 이제 PDF 밑에 레퍼런셜 컨스트롤인테스라고 하는 삭제 수정 규칙 룰을 가면 되는데.",
            "<11:05:06> 이렇게 내가 지금 업데이트 셋 문이에요.",
            "<11:19:03> 하고 내용을 보고 다시 롤백을 원래대로 돌아가더라.",
            "<11:19:28> 그래서 롤백이 인서트 딜리트 업데이트 한 거를 되돌린까지는 일단 우리가 확인했어요."
          ],
          "reasoning": "강사가 수강생에게 직접적인 참여를 유도하며, 함께 작업을 진행하도록 하고 있습니다. 참여 유도가 자주 이루어지지만, 더 다양한 형태의 참여를 유도할 수 있었던 점에서 4점으로 평가했습니다. | 수강생의 참여를 유도하는 시도가 있으나, 빈도가 낮고 형식적인 부분이 있음. | 수강생 참여를 유도하는 표현이 있으나, 빈도가 낮고 형식적인 참여 유도에 그치는 경향이 있음.",
          "confidence": 0.76,
          "caveats": [
            "참여 유도가 있지만, 수강생의 적극적인 참여를 이끌어내는 데 한계가 있을 수 있음",
            "수강생의 반응이 명확하지 않아 참여 유도 정도를 정확히 판단하기 어려움",
            "참여 유도 표현이 명확하지 않을 수 있음",
            "참여 유도 표현이 다소 제한적임",
            "강의 내용이 짧아 참여 유도 여부를 판단하기 어려움"
          ]
        },
        {
          "item_id": "5.4",
          "item_name": "질문 응답 충분성",
          "category": "5. 수강생 상호작용",
          "score": 3,
          "weight": "HIGH",
          "evidence": [
            "<09:39:47> 이렇게 해서 약간 기준은 뭐야? 좀 궁금하지 않으세요.",
            "<09:57:58> 410d984d: 자식 테이블에 참조하고 있으므로 삭제 거부된다.",
            "<10:10:30> 맞아 그래서 이 말이 뭐냐 말이 이렇게 비식별 관계에서는 자식 테이블의 데이터를 삭제하거나 수정할 때 부모 테이블의 식별 체계에다가 혼란을 주지 않는다.",
            "<10:35:25> 뭐가 나왔어요.",
            "<10:39:30> 여기서 직접적으로 건드릴 지금 현재 우리가 대만 지금 건드리고 있는 거지.",
            "<11:19:21> 이러면 롤백이야 자 되셨어요. 옳지",
            "<11:26:08> 이러면 여기 오토 인클라이먼트야 그 다음에 여기는 GF가 뭐야? 그러면 여기는 제로 피리어 이런 것들을 이렇게 사용하고",
            "<11:44:14> 네 이렇게 해서 하시고 오후에는 제가 이 내용이랑 트랜잭션이랑 이런 것들을 조금 하면서 트윗 이런 것들 이게 지금 이걸로 뭐 관리하고 이런 거 있거든요.",
            "<01:21:39> 이런 거랑 똑같아요.",
            "<01:29:27> 이렇게 돌아가겠다까지 설명 이거 이제 아침에 했기 때문에 코드는 코딩 안 해도 볼 수 있단 말이에야 사보작 이런 내용들이 있어요."
          ],
          "reasoning": "강사가 수강생의 질문에 대해 명확하게 답변하고 있으며, 추가적인 설명을 통해 이해를 돕고 있습니다. 그러나 일부 질문에 대한 답변이 간략하여 보충 설명이 필요할 수 있습니다. | 수강생 질문에 대해 명확하고 충분한 답변을 제공하고 있으며, 관련 배경 지식도 함께 설명하고 있음. | 수강생 질문에 대해 명확하고 충분한 답변을 제공하며, 관련 배경 지식도 함께 설명하고 있음.",
          "confidence": 0.77,
          "caveats": [
            "질문 응답이 구체적이지 않음",
            "일부 질문에 대한 답변이 간략할 수 있음",
            "질문 응답의 구체성이 부족할 수 있음",
            "질문이 명확하지 않아 답변이 제한적일 수 있음",
            "질문에 대한 구체적인 내용이 부족할 수 있음"
          ]
        }
      ],
      "weighted_average": 2.8181818181818183
    }
  ],
  "weighted_average": 3.1777777777777776,
  "weighted_total": 143.0,
  "category_averages": {
    "1. 언어 표현 품질": 3.2857142857142856,
    "2. 강의 도입 및 구조": 3.272727272727273,
    "3. 개념 설명 명확성": 3.2,
    "4. 예시 및 실습 연계": 3.5,
    "5. 수강생 상호작용": 2.8181818181818183
  },
  "category_scores": {
    "1. 언어 표현 품질": [
      {
        "item_id": "1.1",
        "item_name": "불필요한 반복 표현",
        "category": "1. 언어 표현 품질",
        "score": 3,
        "weight": "HIGH",
        "evidence": [
          "<09:10:57> ... 이제 ...",
          "<09:12:11> ... 저희가 이제 ...",
          "<09:16:01> ... 얘를 하면서 얘를 구현하는 내용이라 ...",
          "<09:35:45> ... 지금 현재 이제 ...",
          "<09:39:11> ... 자식이 되는 거야.",
          "<09:39:18> ... 그러면 살짝 이거를 지금 현재 이 구조 ...",
          "<09:45:30> ... 이렇게 해서 정리 살짝 이렇게 세 가지고 있으면 ...",
          "<09:46:04> ... 그래서 지금 현재 어제 했던 그 마지막 ...",
          "<09:57:06> ... 그럼 생성 자체가 불가능해 FK가 불가능해 ...",
          "<10:01:24> ... 그래서 연결되어 있지 않고 연결이 되어 있어도 ..."
        ],
        "reasoning": "습관적 표현 '이제'와 '저희가 이제'가 해당 구간에서 분당 약 4회 관찰됨. 반복이 있지만 내용 전달에 큰 문제는 없음. | 습관적 표현 '지금 현재', '이제', '살짝' 등이 반복적으로 사용되어 강의 흐름을 방해함. | 반복 표현 '독립'과 '비식별 관계'가 빈번하게 나타나 강의 흐름을 방해함. 특히 '독립'이라는 표현이 여러 번 반복됨.",
        "confidence": 0.76,
        "caveats": [
          "STT 오인식으로 인한 반복 가능성 일부 존재"
        ]
      },
      {
        "item_id": "1.2",
        "item_name": "발화 완결성",
        "category": "1. 언어 표현 품질",
        "score": 3,
        "weight": "MEDIUM",
        "evidence": [
          "<09:11:35> ... 시스 스키마라는 것을 가지고 ...",
          "<09:12:23> ... 이렇게 해서 세 가지 카테고리를 가지고 ...",
          "<09:37:21> ... 그래서 ...",
          "<09:39:39> ... 작성을 하다 보면 내가 나도 모르게 자식이 되고 ...",
          "<09:40:04> ... 약간 이런 먼저 만들어져서 약간 이런 느낌도 맞아 ...",
          "<09:57:58> ... 자식 테이블에 참조하고 있으므로 삭제 거부된다.",
          "<10:01:21> ... 그래서 얘가 이렇게 표시가 된다고 했어요.",
          "<10:02:12> ... 끊어버리는 거지 따다 부모 자식 관계는 있지만 내가 PK값 안 받아도 돼 나 돈이 있어.",
          "<10:10:41> ... 얘기가 캐스케이드 옵션이 있기 때문이고 노액션 옵션이 있기 때문에 온 딜리트 온 업데이트 식별관계는 한다.",
          "<10:25:43> ... 연결되어었을 때 CRD를 하게 되면 어떤 역량을 가질 수 있는지를 우리가 한눈에 볼 수 있 ..."
        ],
        "reasoning": "대체로 문장이 완결되며, 간혹 비완결 문장이 나타나지만 이해에 문제 없음. | 비완결 문장이 간헐적으로 나타나며, 때로 의미 파악이 어려운 경우가 있음. | 비완결 문장이 간간이 나타나며, 특히 문장 중간에 주제가 전환되는 경우가 있어 수강생이 의미를 추론해야 하는 경우가 발생.",
        "confidence": 0.71,
        "caveats": [
          "STT 오류로 인한 문장 끊김은 감점 대상에서 제외"
        ]
      },
      {
        "item_id": "1.3",
        "item_name": "언어 일관성",
        "category": "1. 언어 표현 품질",
        "score": 4,
        "weight": "MEDIUM",
        "evidence": [
          "<09:10:38> ... 안녕하세요.",
          "<09:10:41> ... 저희 수업 진행하도록 하겠습니다.",
          "<09:35:38> ... 됐습니까?",
          "<09:39:11> ... 자식이 되는 거야.",
          "<09:39:18> ... 그러면 살짝 이거를 ...",
          "<09:45:30> ... 이렇게 해서 정리 살짝 ...",
          "<09:57:06> ... 그럼 생성 자체가 불가능해 FK가 불가능해 ...",
          "<10:00:44> ... 제가 이렇게 해서 말씀드렸는데.",
          "<10:01:00> ... 내가 뭐라고 그랬어요. 그렇지.",
          "<10:11:10> ... 그러면 다시 원래대로 가도록 하겠습니다."
        ],
        "reasoning": "대체로 존댓말로 일관되지만, 특정 구간에서 반말이 혼용되어 어색함이 관찰됨. | 대체로 일관되지만 특정 구간에서 존댓말과 반말이 혼용되어 어색함. | 대체로 존댓말이 사용되지만, 특정 구간에서 반말이 혼용되어 어색함이 느껴짐. 그러나 전반적으로는 일관성이 유지됨.",
        "confidence": 0.78,
        "caveats": [
          "수강생과 대화 시 톤 변화는 자연스러운 것으로 봄"
        ]
      }
    ],
    "2. 강의 도입 및 구조": [
      {
        "item_id": "2.1",
        "item_name": "학습 목표 안내",
        "category": "2. 강의 도입 및 구조",
        "score": 4,
        "weight": "HIGH",
        "evidence": [
          "<09:10:57> 저희 이제 오늘은 13일 수업이고 그 다음에 오늘 수업 끝나면 이제 연휴라서 오늘 좀 행복하게 수업 진행해 보도록 할 저희 어제는 그 마이에스큐L이 가지고 있는 크레트 구먼을 어제 진행을 하셨습니다데..."
        ],
        "reasoning": "강의 시작 후 2분 내에 학습 목표를 언급하고, 어제의 내용을 간략히 설명하며 오늘의 수업 흐름을 안내함.",
        "confidence": 0.85,
        "caveats": []
      },
      {
        "item_id": "2.2",
        "item_name": "전날 복습 연계",
        "category": "2. 강의 도입 및 구조",
        "score": 5,
        "weight": "HIGH",
        "evidence": [
          "<09:10:57> 저희 어제는 그 마이에스큐L이 가지고 있는 크레트 구먼을 어제 진행을 하셨습니다데..."
        ],
        "reasoning": "어제의 수업 내용을 명확히 복습하고, 오늘의 수업과의 연결고리를 자연스럽게 설명함.",
        "confidence": 0.9,
        "caveats": []
      },
      {
        "item_id": "2.3",
        "item_name": "설명 순서",
        "category": "2. 강의 도입 및 구조",
        "score": 2,
        "weight": "MEDIUM",
        "evidence": [
          "<09:14:10> 이제 저희가 백엔드 프로그램을 하고 있기 때문에 이 트랜잭션을 어떻게 관리하는지를 알아야 저희가 이제 세션이 물려 있을 때 클라이언트가 서버에 접속했을 때 락을 건 상태에서 데이터 CRD의 보존성을 트랜잭션으로 저희가 관리를 할 수가 있습니다.",
          "<09:39:18> 그러면 살짝 이거를 지금 현재 이 구조 여기 지금 스턴트 마이에서 지금 제가 작성을 조금 해드리도록 하겠습니다.",
          "<10:10:30> 비식별 관계를 생각했을 때 데이터 무결성을 반드시 알아야 된다.",
          "<10:35:11> 오늘은 아침에 그렇게 어렵지 않죠 여기 이제 오늘 저희가 이제 그 아침부터 비식별 관계를 설명하고 참조를 지금 설명하고 있는데,",
          "<11:15:02> DDL은 버퍼를 사용하지 않고 알터 이런 명령들이지 이게 DDL 데이터 정의어인데 얘는 실행 즉시 커밋이 실제 데이터 디스크 상태로 저장하는 애야...",
          "<11:19:28> 그래서 롤백이 인서트 딜리트 업데이트 한 거를 되돌린까지는 일단 우리가 확인했어요.",
          "<11:40:38> 이해 가요 이런 식으로 가는 게 트랜잭션의 원리인 거야.",
          "<01:17:50> 트랜잭션의 특징은 이건 시험 문제 필수 트랜잭션은 원래 ACID 원칙이라는 게 맨 처음에 나오자마자...",
          "<01:22:15> 일단은 이런 역할들이 있고 이런 명령어까지 있어요.",
          "<01:23:11> 그러면 여기 앞에랑기 커밋이야 그래서 지금 이거 URL 3개 섹션을 지금 스레드에다가 공유를 해드렸잖아요."
        ],
        "reasoning": "대체로 구조적이며 개념, 예시, 실습의 흐름이 자연스러움. 그러나 일부 단계 간 전환이 명시적이지 않음. | 개념, 예시, 실습의 순서가 혼재되어 있으며, 설명의 흐름이 일관되지 않음. | 구조가 있지만 때때로 순서가 뒤바뀌거나 단계가 생략됨.",
        "confidence": 0.73,
        "caveats": []
      },
      {
        "item_id": "2.4",
        "item_name": "핵심 내용 강조",
        "category": "2. 강의 도입 및 구조",
        "score": 2,
        "weight": "MEDIUM",
        "evidence": [
          "<09:15:53> 오늘은 핵심이 인서트 딜리트 업데이트가 얘니다.",
          "<09:46:32> 부모 테이블의 3대 필수 요건으로 대신할 수 있어 지금 제가 말은 이렇게 적어놨는데 이게 지금",
          "<10:10:30> 비식별 관계를 생각했을 때 데이터 무결성을 반드시 알아야 된다.",
          "<10:34:44> 외래키 맵핑 정보라고 제가 써놨어요.",
          "<11:15:34> 그래서 얘는 트랜젝션 취소 대상에 포함되지 않아 빼이 불가능해 하여 벌써 저장해버렸어 롤백 불가능...",
          "<11:40:50> 이해 가요 이런 식으로 가는 게 트랜잭션의 원리인 거야.",
          "<11:40:38> 이해 가요 이런 식으로 가는 게 트랜잭션의 원리인 거야.",
          "<01:17:50> 트랜잭션은 원래 ACID 원칙이라는 게 맨 처음에 나오자마자...",
          "<01:31:01> 내가 내 맘대로 커밋하고 내가 내 맘대로 인서트 한 사람이 커밋하고 인서트 한 사람이 롤백 해야 되는 거 아니냐.",
          "<01:56:39> 아시겠죠."
        ],
        "reasoning": "핵심 내용을 자연스럽게 반복하여 설명하고 강조함. 그러나 일부 중요한 내용은 강조가 부족할 수 있음. | 일부 중요한 내용을 강조하지만, 체계적이지 않음. | 핵심 내용을 자연스럽게 반복하여 설명하고 강조함.",
        "confidence": 0.73,
        "caveats": []
      },
      {
        "item_id": "2.5",
        "item_name": "마무리 요약",
        "category": "2. 강의 도입 및 구조",
        "score": 1,
        "weight": "LOW",
        "evidence": [
          "<05:50:05> 여러분 한 주간 고생 많으셨습니다.",
          "<05:50:21> 시간 명절 잘 보내시고 잘 쉬시고 기분 좋게 6월 23일 날 뵙도록 할게요 수고하셨습니다."
        ],
        "reasoning": "강의 마무리 요약이 전혀 없으며, 강의가 종료되는 형식으로만 진행되고 있습니다.",
        "confidence": 0.9,
        "caveats": []
      }
    ],
    "3. 개념 설명 명확성": [
      {
        "item_id": "3.1",
        "item_name": "개념 정의",
        "category": "3. 개념 설명 명확성",
        "score": 3,
        "weight": "HIGH",
        "evidence": [
          "<09:14:10> 이제 저희가 백엔드 프로그램을 하고 있기 때문에 이 트랜잭션을 어떻게 관리하는지를 알아야 저희가 이제 세션이 물려 있을 때 클라이언트가 서버에 접속했을 때 락을 건 상태에서 데이터 CRD의 보존성을 트랜잭션으로 저희가 관리를 할 수가 있습니다.",
          "<09:39:18> 그러면 살짝 이거를 지금 현재 이 구조 여기 지금 스턴트 마이에서 지금 제가 작성을 조금 해드리도록 하겠습니다.",
          "<10:01:39> 그래서 연결되어 있지 않고 연결이 되어 있어도 그냥 직선으로 연결되 있는 게 아니라 나는 나 따로 독립했으니까 지원 안 받아도 돼 그래서 얘가 이렇게 표시가 된다고 했어요.",
          "<10:35:11> 비식별 관계를 설명하고 참조를 지금 설명하고 있는데, 여기에서 얘 같은 경우에는 전용 참조 테이블의 정보를 가지고 이거는 크 컨스트레인티스를 가지고 이거 했더니, 뭐가 나왔어요.",
          "<11:04:27> 자 그 다음에 언더바 EMP 테이블에 자 여기 제약 조건을 하나 칼럼을 추가를 해보자 이렇게 해서 하나 이렇게 살짝 까시고 CMP로 확인을 한번",
          "<11:17:26> 롤백 커밋 중에 두 개를 하겠다는 건데 이렇게가 롤백이야 이렇게 해서 하나 살짝 정리 여기서는 정시적인 트랜잭션 종료를 하는 명령어 하트 트랜잭션이라는 애를 정료하는 롤백이고 마지막 코밋 스타트 트랜잭션 선언했던 트랜잭션의 시작점으로 돌아갑니다.",
          "<11:40:50> 여러 개의 세션이 동일한 데이터를 접속했을 때 최초 접속했던 내용이 스토리지에서 가지고 온 거고, 인서트 딜리트 업데이트가...",
          "<01:13:42> 저희가 이제 개념은 아침에 오전 수업에서 살짝 눈도는 스타트 트랜잭션이라고 하는 것은 트랜잭션 시작을 알리는 거고, 명시적으로 커밋은...",
          "<01:21:39> 이런 거랑 똑같아요어서 나중에 우리가 자바로 데이터베이스에 데이터를 가지고 왔어 게시판을 오픈을 오픈했는데 실제적으로 동시에 뭐 10명이 똑같은 게시글 하나를 가지고는 수정하려고 그러고 하나는 삭제하려고 그러고 이런 것들은 어떻게 처리하는 거예요.",
          "<01:49:19> 0으로 줘야 롤백을 할 수가 있고 자 셋에 가서 오토커밋을 0을 주면 지금 SQL 서버를 서버에서 완전히 변경된다."
        ],
        "reasoning": "트랜잭션 개념이 등장했으나 명확한 정의 없이 사용되고 있어 수강생이 이해하기 어려울 수 있음. | 일부 개념은 정의 없이 사용되지만, 전체적으로 이해에 큰 문제는 없음. 예를 들어, '부모 테이블'과 '자식 테이블'의 개념은 설명되지만 명확한 정의는 부족함. | 강의 중 여러 개념이 언급되지만, 명확한 정의가 부족하여 수강생이 이해하기 어려울 수 있음. 특히 '비식별 관계'와 '식별 관계'에 대한 명확한 설명이 부족함.",
        "confidence": 0.71,
        "caveats": [
          "STT 특성상 기술 용어 인식 오류 가능"
        ]
      },
      {
        "item_id": "3.2",
        "item_name": "비유 및 예시 활용",
        "category": "3. 개념 설명 명확성",
        "score": 3,
        "weight": "HIGH",
        "evidence": [
          "<09:25:03> 말 그대로 릴레이션십이라서 RD를 할 수 있는 테이블 한 개가 아니고 연결되어 있는서 살짝 이런 것들을 물어봐요.",
          "<09:43:40> 예를 들면 회사가 있어야 사원이 있는 거죠서 뎁트 테이블이 먼저 부모가 되는 거고, 그다음에 사원이 EMP 테이블이거든요.",
          "<10:11:00> 독립한 애들의 특징을 가만히 생각해보면 사람 사는 거랑 지금 똑같아 스케프 하겠습니다.",
          "<10:33:38> 여러분들 뭐 조별로 하실 때도 많이 쓰고 이렇게 하는데 좀 익숙해지면 이 워크벤치가 CMD보다 약간 불편할 수 있어요.",
          "<11:12:32> 우리가 익스플레인하고 우리 조인하고 이런 거 하면 거기에 뭐 MT도 나오고 그 다음에 템플러이 테이블도 나오고 막 이런 식으로 해서 돈 계산을 실행 예측이잖아요.",
          "<11:19:10> 그리고 여기서 트랜잭션을 명시적으로 종료하는 명령은 뭐야? 이러면 롤백이야 자 되셨어요. 옳지",
          "<11:40:38> 이해 가요 이런 식으로 가는 게 트랜잭션의 원리인 거야.",
          "<01:20:01> 예를 들어서 어떤 작은 부에 돈이 만 원이 있어 이거를 작은 부 은행은 자금부라는 게 있거든.",
          "<01:31:01> 내가 내 맘대로 롤백하고 내가 내 맘대로 코밋할 수 있게끔 만들어 놨단 말이야.",
          "<01:57:07> 결론은 스타트 트랜잭션은 커밋과 롤백 두 개 중에 하나 만나면 종료가 되는 거고."
        ],
        "reasoning": "비유나 예시가 거의 없어 추상적 설명에 의존하고 있어 이해를 돕지 못함. | 어려운 개념에 대해 실생활 예시를 적절히 활용하고 있으며, 이해에 도움이 됨. 그러나 비유의 빈도가 다소 낮음. | 비유가 사용되긴 했으나, 비유의 빈도가 낮고 구체적인 실생활 예시가 부족하여 이해를 돕는 데 한계가 있음.",
        "confidence": 0.71,
        "caveats": [
          "STT 특성상 비유 표현이 누락되었을 가능성",
          "STT 특성상 비유의 정확한 표현이 어려울 수 있음",
          "STT 특성상 비유 표현이 부정확할 수 있음",
          "STT 특성상 비유 및 예시 인식 오류 가능",
          "STT 특성상 기술 용어 인식 오류 가능"
        ]
      },
      {
        "item_id": "3.3",
        "item_name": "선행 개념 확인",
        "category": "3. 개념 설명 명확성",
        "score": 3,
        "weight": "MEDIUM",
        "evidence": [
          "<09:12:23> 그중에서 테이블에 관련된 거 컬럼에 관련된 계약 조건에 관련된 거 이렇게 해서 세 가지 카테고리를 가지고 테이블을 봤었는데 일반 테이블 같은 경우에는 데이터베이스 생성하고 난 다음에 테이블의 구조를 가지고 있는 속성 값을 가지고 있었고,",
          "<09:39:11> 자식은 부모 눈치 살짝 보면서 참조해서 테이블을 생성해야 되는 이런 상황인 거지 되셨어요.",
          "<10:03:06> 식별은 데이터가 없어도 자식 데이터로 살 수 있는 그렇지 얘기했잖아.",
          "<10:35:25> 어미가 나왔죠 범위 어떻게 체크를 줬는지 끝까지 살짝 정리 여기는 뭐 다시 안 봐도 될 것 같습니다.",
          "<11:10:11> 이렇게 그래서 여기다가 마지막 커밋 명령 또는 스타트 트랜잭션 이렇게로 살짝 돌아가 이렇게 이 시점으로",
          "<11:19:03> 하고 내용을 보고 다시 롤백을 원래대로 돌아가더라 그런데 어디로 돌아가야 돼 마지막 커밋 상태 또는 스타트 트랜잭션이 선언했던 트랜잭션의 시작점으로 되돌아간다.",
          "<11:41:04> 우리가 보통 이렇게 쿼리 조작 언어인데 쿼리 조작 언어를 할 때는 기본적으로 내가 커밋을 할 건지 롤백을 할 건지를 일단은 결정을 해서 작업을 진행하게 된다죠.",
          "<01:18:06> 그러면 데이터에 테이블 생성을 할 때 제약 조건을 생각하시면 그렇게 어렵지 않아요.",
          "<01:22:07> 이런 건 다 서버가 처리하는 거예요.",
          "<01:55:52> 지금 DML 연습해보자 이렇게 했으니까 자 이제 스타트 트랜잭션 하겠다."
        ],
        "reasoning": "선행 개념을 고려하여 설명하고 있으나, 일부 심화 내용으로의 점프가 존재함. | 대체로 선행 개념을 고려하며 설명하고 있으나, 가끔 심화 내용으로 넘어가는 경향이 있음. | 선행 개념에 대한 언급이 있지만, 때때로 심화 내용으로 넘어가는 경향이 있어 수강생이 따라가기 어려울 수 있음.",
        "confidence": 0.69,
        "caveats": [
          "STT 특성상 문맥이 불명확할 수 있음",
          "STT 특성상 문장 경계 인식 오류 가능",
          "STT 특성상 기술 용어 인식 오류 가능",
          "STT 특성상 문장 경계가 불명확할 수 있음"
        ]
      },
      {
        "item_id": "3.4",
        "item_name": "발화 속도 적절성",
        "category": "3. 개념 설명 명확성",
        "score": 4,
        "weight": "MEDIUM",
        "evidence": [
          "<09:14:45> 그래서 커믹과 롤백이라는 것을 잘 이용을 해서 무결성을 또 다른 서버나 아니면 클라이언트에게 어떻게 보여지는지 오늘 좀 확인할 거고,",
          "<09:46:32> 횟수 조건이 3번 기준인데 부모 테이블의 3대 필수 요건으로 대신할 수 있어 지금 제가 말은 이렇게 적어놨는데 이게 지금",
          "<10:10:30> 맞아 그래서 이 말이 뭐냐 말이 이렇게 비식별 관계에서는 자식 테이블의 데이터를 삭제하거나 수정할 때 부모 테이블의 식별 체계에다가 혼란을 주지 않는다.",
          "<10:34:09> 저도 여기서 코딩할 때랑 여기 CMD에서 코딩할 때랑 속도가 조금 다르거든요.",
          "<11:12:34> 실행 예측식 그래서 실행 예측 시간이라고 강사가 매번 얘기하고 그 다음에 실행 비용을 체크하겠다.",
          "<11:40:00> 이해 가요 이런 식으로 가는 게 트랜잭션의 원리인 거야.",
          "<11:42:54> 좀 답다해 정신 없다어 우기꺼 이제 알고는 있지만...",
          "<01:21:14> 해줘야 되는 거예서 동시에 여러 트랜잭션이 접근을 하게 되면 충돌이 발생할 수 있기 때문에 서버는 락이나 격리 수준 관리를 진행하게 된다.",
          "<01:30:20> 오토커밋 변수가 나와서 지금 시스템 배리어블리 기본값이 지금 오늘 어떻게 되어있는지 조금 이따 찾아보면 되는 거니까.",
          "<02:00:34> 실제 데이터가 생존해 있다는 거지 생존했어."
        ],
        "reasoning": "발화 속도가 일정하나 때때로 빠르거나 느려 조절이 부족하여 집중에 방해가 될 수 있음. | 속도가 일정하나 때때로 빠르거나 느려 조절이 부족하여 집중에 방해가 될 수 있음. | 전반적으로 발화 속도가 적절하나, 일부 구간에서 빠르게 진행되어 집중에 방해가 될 수 있음.",
        "confidence": 0.72,
        "caveats": [
          "STT 특성상 발화 속도 인식 오류 가능",
          "타임스탬프 간격으로 발화 밀도 추정",
          "타임스탬프 간격으로 발화 밀도 추정 필요",
          "STT 특성상 기술 용어 인식 오류 가능",
          "STT 특성상 발화 속도에 대한 인식 오류 가능"
        ]
      }
    ],
    "4. 예시 및 실습 연계": [
      {
        "item_id": "4.1",
        "item_name": "예시 적절성",
        "category": "4. 예시 및 실습 연계",
        "score": 3,
        "weight": "HIGH",
        "evidence": [
          "<09:24:00> 이러면 테이블이 두 개가 릴레이션십이 되어 있는데, 기타 등등 얘기하면 프로시저하고 펑션의 사용성 이런 것들 물어보고 인제 아주 편안한 대화 이런 것들을 물어봅니다.",
          "<09:43:40> 예를 들면 회사가 있어야 사원이 있는 거죠서 뎁트 테이블이 먼저 부모가 되는 거고, 그다음에 사원이 EMP 테이블이거든요.",
          "<10:15:10> 예를 들면 상품 테이블 주문 테이블 하나 만들어 가지고...",
          "<10:30:05> 예를 들자면 뭐 이거나 얘나 FK 있는 애들 살짝 보세런 애들은...",
          "<11:02:14> 자 이렇게 해서 잠깐 이렇게 해서 드려야 되는데 이거 제가 어디서 하냐면 저는 VS코드도 연결해가지고 시퀀 쓰고 하니까 정렬하면 한 줄로 이렇게",
          "<11:19:10> 그리고 여기서 트랜잭션을 명시적으로 종료하는 명령은 뭐야? 이러면 롤백이야 자 되셨어요. 옳지",
          "<11:42:02> 그래서 이게 계약 조건이 추가 삭제 수정이 힘들어서 추가 수정 삭제하는 방법을 여기다가 살짝 적어놓고 유니크는 여기서 드랍 인덱스라는 걸로 하더라 까지 확인 내용으로 살짝 정리를 한번 하시면 어떨까",
          "<01:20:01> 예를 들어서 어떤 작은 부에 돈이 만 원이 있어 이거를 작은 부 은행은 자금부라는 게 있거든.",
          "<01:21:39> 이런 거랑 똑같아요어서 나중에 우리가 자바로 데이터베이스에 데이터를 가지고 왔어 게시판을 오픈을 오픈했는데 실제적으로 동시에 뭐 10명이 똑같은 게시글 하나를 가지고는 수정하려고 그러고 하나는 삭제하려고 그러고 이런 것들은 어떻게 처리하는 거예요.",
          "<01:55:52> 지금 DML 연습해보자 이렇게 했으니까 자 이제 스타트 트랜잭션 하겠다."
        ],
        "reasoning": "강의 중에 실제 데이터베이스의 테이블 간 관계를 설명하며, 프로시저와 펑션의 사용성을 예로 들어 실무에서의 적용 가능성을 언급하고 있어 수강생들이 이해하기 쉽게 연결되고 있습니다. | 강의에서 부모-자식 관계를 설명할 때, 실제 회사와 사원 간의 관계를 예로 들어 설명하여 수강생들이 이해하기 쉽게 연결하였습니다. | 강사가 실제 데이터베이스 설계와 관련된 예시를 통해 이론을 설명하고 있어, 수강생들이 실무에서 접할 수 있는 상황과 연관성이 높음.",
        "confidence": 0.77,
        "caveats": []
      },
      {
        "item_id": "4.2",
        "item_name": "실습 연계",
        "category": "4. 예시 및 실습 연계",
        "score": 4,
        "weight": "HIGH",
        "evidence": [
          "<09:27:12> 오늘 CRD라고 하는 파일 하나 드렸죠 네 이거 하나 살펴보면 어제 했던 내용들을 살짝 정리를 조금 트랜잭션이랑 해놓은 게 있으니까 이거 조금 보도록 할게요.",
          "<09:52:14> 이렇게 해서 온 딜리트 부모가 지금 현재 부모가요 삭제 뭐 수정되면식도 함께 삭제 수정되겠다.",
          "<10:12:02> 포린키 제약 조건 시 선택 옵션이라는 것이 있어요.",
          "<10:35:11> 오늘은 아침에 그렇게 어렵지 않죠 여기 이제 오늘 저희가 이제 그 아침부터 비식별 관계를 설명하고 참조를 지금 설명하고 있는데...",
          "<11:01:33> 자 이제 저희 그 풀이 잠깐 보고 오늘 수업 진행하도록 진도 나가도록 할게요 일단은 유즈 마이 EMP로 갑니다.",
          "<11:19:28> 그래서 롤백이 인서트 딜리트 업데이트 한 거를 되돌린까지는 일단 우리가 확인했어요.",
          "<11:36:20> 이런 거지 그다음에 이런 거 있으면 항상 얘도 넣어보고 싶어 물론 알고는 있지만 얘도 넣어보고 싶어 이렇게 그러면은 이제 키값이 하나 살짝 들어가 있으니까",
          "<11:44:14> 네 이렇게 해서 하시고 오후에는 제가 이 내용이랑 트랜잭션이랑 이런 것들을 조금 하면서 트윗 이런 것들 이게 지금 이걸로 뭐 관리하고 이런 거 있거든요.",
          "<01:25:01> 이해 가죠 스케이프 하고요. 그 다음에 여기다가 이제 트랜잭션이라고 하나 입력을 해볼다.",
          "<01:29:04> DML 작업에 대한 내용 그래서 사부작 하면 글 하나 만들어서 하트 트랜잭션하고 콘서트 한 다음에 서밋을 하는 거지 그리고 나서 여기에 셋 오토 커밋을스로 주고"
        ],
        "reasoning": "이론 설명 후 실습으로 자연스럽게 연결되며, 실습 내용이 이론과 관련되어 있어 수강생들이 직접 실습을 통해 이론을 강화할 수 있도록 잘 안내하고 있습니다. | 이론 설명 후 실습으로 자연스럽게 연결되었으나, 실습에 대한 명확한 전환 표현이 부족하여 연결이 다소 느슨하게 느껴졌습니다. | 이론 설명 후 실습으로 자연스럽게 연결되며, 실습 내용이 이론과 밀접하게 관련되어 있음. 강사가 실습을 통해 이론을 강화하는 방식으로 진행.",
        "confidence": 0.79,
        "caveats": []
      }
    ],
    "5. 수강생 상호작용": [
      {
        "item_id": "5.1",
        "item_name": "오류 대응",
        "category": "5. 수강생 상호작용",
        "score": 2,
        "weight": "MEDIUM",
        "evidence": [
          "<09:29:33> 죄송합니다. 어제 이거 삭제 안하고 걸어놓고 갔나 봐",
          "<09:30:02> 그래서 지금 드랍이 안 되는 상태",
          "<09:51:06> 410d984d: 1215부터 시작해서 1255 몇 개 되지 않다 천 단위 몇 개 아니라서 1225 오류가 발생한다.",
          "<10:07:03> 여기까지 확인하셨을까요?",
          "<10:10:30> 맞아 그래서 이 말이 뭐냐 말이 이렇게 비식별 관계에서는 자식 테이블의 데이터를 삭제하거나 수정할 때 부모 테이블의 식별 체계에다가 혼란을 주지 않는다.",
          "<11:05:22> 아직까지 공부는 안 했지만, 업데이트 샘문이야 아 수정하겠어 그래 퀘스트 언더바 이제 EMP에 4를 전부 다 천으로 세팅하겠죠.",
          "<11:18:09> 그런데 강사님 나 지금 원래대로 돌아가지 않아 이렇게 얘가 지금 현재 오토코밋을 자동 저장 자동 저장을 뭐 1로 놨겠지 그건 이따 가서 한번 보자고요.",
          "<11:41:23> 내가 커밋을 할 건지 롤백을 할 건지를 일단은 결정을 해서 작업을 진행하게 된다죠 지금은 뭐 이게 지금 데이터가 커밋하든 롤백하든 지금 이렇게 여러분들이 이제 눈으로 확인하시면 되고요.",
          "<01:20:01> 이거를 트랜잭션으로 가져오기 시작하면 한쪽은 롤백 하려고 한쪽은 커밋하려고 하고 어떤 작업이랑 동일한 형태가 만들어져서 동시성 제어라고 하는 것은 하나의 데이터를 전혀 다른 곳에서 접속을 해서 전혀 다른 일을 하려고 하는 거야.",
          "<01:25:33> 여기다가 이제 트랜잭션이라고 하나 입력을 해볼다 지금 알아서 찾는구나 이게 A랑 왜 이렇게 안 눌러지는 거예요."
        ],
        "reasoning": "강사가 오류 발생 시 즉각적으로 상황을 인지하고 사과하며, 문제의 원인을 설명하고 있습니다. 다만, 해결 방법에 대한 구체적인 설명이 부족하여 4점으로 평가했습니다. | 강사가 오류에 대해 언급했지만, 구체적인 해결 방법이나 디버깅 과정에 대한 설명이 부족함. | 오류 발생 시 강사가 적절히 대응하고 있지만, 설명이 다소 간략하여 수강생이 혼란스러울 수 있는 부분이 있음.",
        "confidence": 0.77,
        "caveats": [
          "오류 발생에 대한 구체적인 대응이 부족하여 수강생의 혼란을 초래할 수 있음.",
          "수강생의 질문이 명확하지 않아 강사의 대응이 제한적일 수 있음",
          "오류 발생 여부가 명확하지 않음",
          "구체적인 오류 상황이 명시되지 않아 평가에 한계가 있음",
          "강의 내용이 짧아 오류 발생 여부를 판단하기 어려움"
        ]
      },
      {
        "item_id": "5.2",
        "item_name": "이해 확인 질문",
        "category": "5. 수강생 상호작용",
        "score": 3,
        "weight": "HIGH",
        "evidence": [
          "<09:39:11> 이해 가셨죠 여기서 참조하는 방향에 있는 테이블명이 모두 부모 테이블",
          "<09:39:18> 되셨어요. 네 좋아요.",
          "<09:39:11> 410d984d: 되셨어요. 네 좋아요.",
          "<09:45:30> 410d984d: 됐을까요?",
          "<10:07:03> 여기까지 확인하셨을까요?",
          "<10:08:20> 여기까지 되셨어요.",
          "<10:27:28> 되셨어요?",
          "<10:34:21> 됐어요.",
          "<11:19:10> 강사 여기 이제 0보다 1배만 받겠다고 해서 업데이트를 CRD 하니까 한번 써본 거 그래서 나는 업데이트 샘 업데이트는 테이블을 가져다가 전체 조건 없이 손으로 변경을 하겠다.",
          "<11:19:21> 이러면 롤백이야 자 되셨어요. 옳지"
        ],
        "reasoning": "이해 확인 질문이 있으나 빈도가 낮고, 질문이 형식적이며 수강생의 이해도를 깊이 있게 점검하지 못하고 있습니다. | 주요 개념 설명 후 이해 확인 질문을 주기적으로 활용하고 있으며, 수강생의 이해도를 점검하는 질문을 하고 있음. | 주요 개념 설명 후 이해 확인 질문을 자주 하며, 수강생의 이해도를 점검하는 질문을 활용하고 있음.",
        "confidence": 0.81,
        "caveats": [
          "일부 질문이 수강생의 이해도를 깊이 있게 점검하지 못할 수 있음",
          "이해 확인 질문이 있지만, 수강생의 반응을 확인할 수 있는 구간이 부족함",
          "화자 구분 부정확으로 일부 확인 질문 누락 가능",
          "일부 확인 질문이 누락될 수 있음.",
          "일부 질문이 형식적일 수 있으며, 수강생의 반응이 명확하지 않음."
        ]
      },
      {
        "item_id": "5.3",
        "item_name": "참여 유도",
        "category": "5. 수강생 상호작용",
        "score": 3,
        "weight": "HIGH",
        "evidence": [
          "<09:28:06> 8로 살짝 오셔서 드랍 좀 하고요.",
          "<09:31:32> 그러면 여기가 지금 스튜던트스 얘거든요.",
          "<09:39:32> 410d984d: 그래서 여기다가 살짝 왜냐하면, 지금 저쪽 워크벤치에다가 제가 위에다가 그릴 수가 없어서 여기다가 살짝 적어드릴게요.",
          "<10:12:02> 프리 들어가서 한번 샤부작 같이 돌려보도록 하겠습니다.",
          "<10:10:47> 정리하는 그런 또 시간이 있겠죠.",
          "<10:26:09> 혼자 풀이한다고 그랬죠 풀이 한번 열어보도록 하겠습니다.",
          "<10:28:30> 애들은 좀 많지만으니까 옳지 이제 밑에 이제 PDF 밑에 레퍼런셜 컨스트롤인테스라고 하는 삭제 수정 규칙 룰을 가면 되는데.",
          "<11:05:06> 이렇게 내가 지금 업데이트 셋 문이에요.",
          "<11:19:03> 하고 내용을 보고 다시 롤백을 원래대로 돌아가더라.",
          "<11:19:28> 그래서 롤백이 인서트 딜리트 업데이트 한 거를 되돌린까지는 일단 우리가 확인했어요."
        ],
        "reasoning": "강사가 수강생에게 직접적인 참여를 유도하며, 함께 작업을 진행하도록 하고 있습니다. 참여 유도가 자주 이루어지지만, 더 다양한 형태의 참여를 유도할 수 있었던 점에서 4점으로 평가했습니다. | 수강생의 참여를 유도하는 시도가 있으나, 빈도가 낮고 형식적인 부분이 있음. | 수강생 참여를 유도하는 표현이 있으나, 빈도가 낮고 형식적인 참여 유도에 그치는 경향이 있음.",
        "confidence": 0.76,
        "caveats": [
          "참여 유도가 있지만, 수강생의 적극적인 참여를 이끌어내는 데 한계가 있을 수 있음",
          "수강생의 반응이 명확하지 않아 참여 유도 정도를 정확히 판단하기 어려움",
          "참여 유도 표현이 명확하지 않을 수 있음",
          "참여 유도 표현이 다소 제한적임",
          "강의 내용이 짧아 참여 유도 여부를 판단하기 어려움"
        ]
      },
      {
        "item_id": "5.4",
        "item_name": "질문 응답 충분성",
        "category": "5. 수강생 상호작용",
        "score": 3,
        "weight": "HIGH",
        "evidence": [
          "<09:39:47> 이렇게 해서 약간 기준은 뭐야? 좀 궁금하지 않으세요.",
          "<09:57:58> 410d984d: 자식 테이블에 참조하고 있으므로 삭제 거부된다.",
          "<10:10:30> 맞아 그래서 이 말이 뭐냐 말이 이렇게 비식별 관계에서는 자식 테이블의 데이터를 삭제하거나 수정할 때 부모 테이블의 식별 체계에다가 혼란을 주지 않는다.",
          "<10:35:25> 뭐가 나왔어요.",
          "<10:39:30> 여기서 직접적으로 건드릴 지금 현재 우리가 대만 지금 건드리고 있는 거지.",
          "<11:19:21> 이러면 롤백이야 자 되셨어요. 옳지",
          "<11:26:08> 이러면 여기 오토 인클라이먼트야 그 다음에 여기는 GF가 뭐야? 그러면 여기는 제로 피리어 이런 것들을 이렇게 사용하고",
          "<11:44:14> 네 이렇게 해서 하시고 오후에는 제가 이 내용이랑 트랜잭션이랑 이런 것들을 조금 하면서 트윗 이런 것들 이게 지금 이걸로 뭐 관리하고 이런 거 있거든요.",
          "<01:21:39> 이런 거랑 똑같아요.",
          "<01:29:27> 이렇게 돌아가겠다까지 설명 이거 이제 아침에 했기 때문에 코드는 코딩 안 해도 볼 수 있단 말이에야 사보작 이런 내용들이 있어요."
        ],
        "reasoning": "강사가 수강생의 질문에 대해 명확하게 답변하고 있으며, 추가적인 설명을 통해 이해를 돕고 있습니다. 그러나 일부 질문에 대한 답변이 간략하여 보충 설명이 필요할 수 있습니다. | 수강생 질문에 대해 명확하고 충분한 답변을 제공하고 있으며, 관련 배경 지식도 함께 설명하고 있음. | 수강생 질문에 대해 명확하고 충분한 답변을 제공하며, 관련 배경 지식도 함께 설명하고 있음.",
        "confidence": 0.77,
        "caveats": [
          "질문 응답이 구체적이지 않음",
          "일부 질문에 대한 답변이 간략할 수 있음",
          "질문 응답의 구체성이 부족할 수 있음",
          "질문이 명확하지 않아 답변이 제한적일 수 있음",
          "질문에 대한 구체적인 내용이 부족할 수 있음"
        ]
      }
    ]
  },
  "report_markdown": "# 강의 품질 분석 리포트\n\n## 1. 종합 요약\n- 가중 평균 점수: 3.18 / 5.0\n- 가중 총점: 143.0\n\n전반적으로 강의는 적절한 수준에서 진행되었으나, 언어 표현 품질과 강의 구조에서 개선이 필요합니다. 특히 반복 표현과 마무리 요약 부족이 강의 흐름에 영향을 미쳤습니다. 수강생 상호작용 측면에서도 더 많은 참여 유도가 필요합니다.\n\n## 2. 카테고리별 상세 평가\n### 1. 언어 표현 품질\n- 점수: 3/5\n- 요약: 반복 표현과 비완결 문장이 관찰됨.\n  - [1.1] 불필요한 반복 표현: 3/5\n    - 근거: '이제', '저희가 이제' 등의 표현이 반복됨.\n    - 개선 제안: 반복 표현을 줄이고 다양한 표현을 사용하여 강의 흐름을 개선할 필요가 있음.\n  - [1.2] 발화 완결성: 3/5\n    - 근거: 비완결 문장이 간헐적으로 나타남.\n    - 개선 제안: 문장을 완결짓는 연습을 통해 명확한 전달을 목표로 해야 함.\n  - [1.3] 언어 일관성: 4/5\n    - 근거: 대체로 존댓말 사용이 일관됨.\n\n### 2. 강의 도입 및 구조\n- 점수: 3.2/5\n- 요약: 학습 목표 안내는 잘 이루어졌으나, 마무리 요약이 부족함.\n  - [2.1] 학습 목표 안내: 4/5\n    - 근거: 강의 시작 후 2분 내에 목표를 언급함.\n  - [2.2] 전날 복습 연계: 5/5\n    - 근거: 어제 수업 내용을 잘 연결함.\n  - [2.3] 설명 순서: 2/5\n    - 근거: 설명의 흐름이 일관되지 않음.\n    - 개선 제안: 각 단계 간의 전환을 명확히 하여 설명의 흐름을 개선해야 함.\n  - [2.5] 마무리 요약: 1/5\n    - 근거: 마무리 요약이 전혀 없음.\n    - 개선 제안: 강의 종료 시 핵심 내용을 요약하는 시간을 가져야 함.\n\n### 3. 개념 설명 명확성\n- 점수: 3/5\n- 요약: 개념 정의가 부족하여 이해에 어려움이 있음.\n  - [3.1] 개념 정의: 3/5\n    - 근거: 트랜잭션 개념이 명확히 정의되지 않음.\n    - 개선 제안: 주요 개념에 대한 명확한 정의를 제공해야 함.\n  - [3.2] 비유 및 예시 활용: 3/5\n    - 근거: 비유가 적고 구체적인 예시가 부족함.\n    - 개선 제안: 실생활 예시를 더 많이 활용하여 이해를 돕는 것이 필요함.\n\n### 4. 예시 및 실습 연계\n- 점수: 3.5/5\n- 요약: 이론과 실습의 연결이 잘 이루어졌으나, 예시의 빈도가 낮음.\n  - [4.1] 예시 적절성: 3/5\n    - 근거: 예시가 적절하나 빈도가 낮음.\n    - 개선 제안: 더 많은 예시를 통해 이론을 강화해야 함.\n  - [4.2] 실습 연계: 4/5\n    - 근거: 이론 설명 후 실습으로 잘 연결됨.\n\n### 5. 수강생 상호작용\n- 점수: 2.8/5\n- 요약: 상호작용이 부족하고 참여 유도가 더 필요함.\n  - [5.1] 오류 대응: 2/5\n    - 근거: 오류 발생 시 해결 방법 설명이 부족함.\n    - 개선 제안: 오류 발생 시 구체적인 해결 방법을 제시해야 함.\n  - [5.2] 이해 확인 질문: 3/5\n    - 근거: 질문 빈도가 낮고 형식적임.\n    - 개선 제안: 이해 확인 질문을 더 자주 활용해야 함.\n\n## 3. 잘한 점 (강점)\n- 강의 도입 시 학습 목표를 명확히 안내함.\n- 전날 수업 내용을 잘 복습하여 연결함.\n- 발화 속도가 전반적으로 적절하여 집중하기 좋음.\n\n## 4. 개선 필요 사항\n- 반복 표현이 많아 강의 흐름이 방해받음.\n- 마무리 요약이 전혀 없어 강의 종료가 불명확함.\n- 개념 정의가 부족하여 수강생의 이해에 어려움이 있음.\n\n## 5. 추천 개선 방향\n- 반복 표현을 줄이고 다양한 표현을 사용하기.\n- 강의 종료 시 핵심 내용을 요약하는 시간을 가지기.\n- 주요 개념에 대한 명확한 정의를 제공하기.",
  "strengths": [],
  "improvements": [],
  "recommendations": [],
  "token_usage": {},
  "cost_usd": 0
}