{"lecture_date":"2026-02-25","transcript_path":"2026-02-25_kdt-backendj-21th.txt","metadata":{"course_id":"kdt-backendj-21th","course_name":"백엔드 부트캠프 21기: Java","date":"2026-02-25","subjects":["Back-End Programming"],"contents":["HTTP 통신 개요 및 웹 작동 방식"],"instructor":"김영아","sub_instructors":["김다은","정석현"]},"category_results":[{"category_name":"1. 언어 표현 품질","items":[{"item_id":"1.1","item_name":"불필요한 반복 표현","category":"1. 언어 표현 품질","score":2,"weight":"HIGH","evidence":["습관적 반복 표현 빈번"],"reasoning":"반복 표현 빈번.","confidence":0.85,"caveats":[]},{"item_id":"1.2","item_name":"발화 완결성","category":"1. 언어 표현 품질","score":2,"weight":"MEDIUM","evidence":["미완결 문장 다수"],"reasoning":"완결성 낮음.","confidence":0.8,"caveats":[]},{"item_id":"1.3","item_name":"언어 일관성","category":"1. 언어 표현 품질","score":3,"weight":"MEDIUM","evidence":["존댓말 기본","반말 간헐적"],"reasoning":"존댓말 기조 유지.","confidence":0.8,"caveats":[]}],"weighted_average":2.29},{"category_name":"2. 강의 도입 및 구조","items":[{"item_id":"2.1","item_name":"학습 목표 안내","category":"2. 강의 도입 및 구조","score":4,"weight":"HIGH","evidence":["'인덱스 개념과 필요성, CRD, 사용자 계정 권한'","학습 목표 구체적 안내"],"reasoning":"인덱스/계정관리/트리거 학습 목표 명확.","confidence":0.85,"caveats":[]},{"item_id":"2.2","item_name":"전날 복습 연계","category":"2. 강의 도입 및 구조","score":4,"weight":"HIGH","evidence":["'어제 프로시저 내에서 예외 처리...펑션...파티션'","이전 수업 상세 복습"],"reasoning":"이전 수업 내용 체계적 요약.","confidence":0.85,"caveats":[]},{"item_id":"2.3","item_name":"설명 순서","category":"2. 강의 도입 및 구조","score":3,"weight":"MEDIUM","evidence":["파티션 복습 -> 인덱스 -> 계정 관리 순서"],"reasoning":"논리적 순서 진행.","confidence":0.75,"caveats":[]},{"item_id":"2.4","item_name":"핵심 내용 강조","category":"2. 강의 도입 및 구조","score":3,"weight":"MEDIUM","evidence":["'파티션은 논리적 분할, 물리적 성능'","'인덱스가 있어야 서치도 빠르고'"],"reasoning":"파티션/인덱스 핵심 강조.","confidence":0.75,"caveats":[]},{"item_id":"2.5","item_name":"마무리 요약","category":"2. 강의 도입 및 구조","score":2,"weight":"LOW","evidence":["명시적 마무리 요약 부재"],"reasoning":"마무리 요약 부재.","confidence":0.8,"caveats":[]}],"weighted_average":3.36},{"category_name":"3. 개념 설명 명확성","items":[{"item_id":"3.1","item_name":"개념 정의","category":"3. 개념 설명 명확성","score":3,"weight":"HIGH","evidence":["파티션 4가지 유형(RANGE/LIST/HASH/KEY) 정의","'분할은 논리적이되 성능은 물리적'"],"reasoning":"파티션 유형별 정의 제공.","confidence":0.75,"caveats":[]},{"item_id":"3.2","item_name":"비유 및 예시 활용","category":"3. 개념 설명 명확성","score":3,"weight":"HIGH","evidence":["정보보안법/문서보존법 실무 사례","'369' 파쇄 기간 비유"],"reasoning":"실무 법규 사례를 통한 파티션 필요성 설명.","confidence":0.8,"caveats":[]},{"item_id":"3.3","item_name":"선행 개념 확인","category":"3. 개념 설명 명확성","score":3,"weight":"MEDIUM","evidence":["CREATE TABLE 옵션과 연결","EXPLAIN 활용"],"reasoning":"선행 개념 연결.","confidence":0.75,"caveats":[]},{"item_id":"3.4","item_name":"발화 속도 적절성","category":"3. 개념 설명 명확성","score":2,"weight":"MEDIUM","evidence":["빠른 발화 지속"],"reasoning":"발화 속도 빠름.","confidence":0.7,"caveats":[]}],"weighted_average":2.8},{"category_name":"4. 예시 및 실습 연계","items":[{"item_id":"4.1","item_name":"예시 적절성","category":"4. 예시 및 실습 연계","score":3,"weight":"HIGH","evidence":["파티션 유형별 실습 예시","도움말 참조"],"reasoning":"적절한 예시.","confidence":0.75,"caveats":[]},{"item_id":"4.2","item_name":"실습 연계","category":"4. 예시 및 실습 연계","score":3,"weight":"HIGH","evidence":["파티션 생성 실습","'눈도장 찍고 가자'"],"reasoning":"실습 기회 제공.","confidence":0.7,"caveats":[]}],"weighted_average":3.0},{"category_name":"5. 수강생 상호작용","items":[{"item_id":"5.1","item_name":"오류 대응","category":"5. 수강생 상호작용","score":3,"weight":"MEDIUM","evidence":["파티션 설정 오류 가능성 사전 안내","'조건 추출할 수 있다'"],"reasoning":"오류 예방적 안내 일부 존재.","confidence":0.7,"caveats":[]},{"item_id":"5.2","item_name":"이해 확인 질문","category":"5. 수강생 상호작용","score":3,"weight":"HIGH","evidence":["'됐을까요?'","'이해 가시죠?'"],"reasoning":"확인 질문 빈번.","confidence":0.85,"caveats":[]},{"item_id":"5.3","item_name":"참여 유도","category":"5. 수강생 상호작용","score":2,"weight":"HIGH","evidence":["적극적 참여 유도 제한적"],"reasoning":"참여 유도 미흡.","confidence":0.75,"caveats":[]},{"item_id":"5.4","item_name":"질문 응답 충분성","category":"5. 수강생 상호작용","score":3,"weight":"HIGH","evidence":["면접 관련 실무 팁 제공","'면접할 때 이런 내용들을 많이 물어봐요'"],"reasoning":"면접/실무 관련 부가 정보 제공으로 학생 이해 도움.","confidence":0.7,"caveats":[]}],"weighted_average":2.73}],"weighted_average":2.83,"weighted_total":119.0,"category_averages":{"1. 언어 표현 품질":2.29,"2. 강의 도입 및 구조":3.36,"3. 개념 설명 명확성":2.8,"4. 예시 및 실습 연계":3.0,"5. 수강생 상호작용":2.73},"report_markdown":"# 종합 평가\n\n## 종합 점수: 2.83/5.0\n\n## 강점\n- 파티션 유형별 체계적 설명\n- 정보보안법 등 실무 사례 활용\n- 면접 관련 실무 팁 제공\n\n## 개선 필요\n- 반복 표현 감소\n- 발화 속도 조절","strengths":["파티션 유형별 체계적 설명","정보보안법 등 실무 사례 활용","면접 관련 실무 팁 제공"],"improvements":["반복 표현 감소 필요","발화 속도 조절 필요","학생 참여 유도 강화 필요"],"recommendations":["핵심 개념 정의 사전 준비","마무리 요약 시간 확보","학생 참여 유도 활동 추가"],"token_usage":{},"cost_usd":0}
